Workbook

Sheet Cover
B2: Tema Cocoa Processing Plant — Project Finance Model
B5: 15,000 MT/yr installed capacity cocoa grinding facility — Tema, Ghana
B6: Export offtake (contracted + spot, with price floor & take-or-pay) | Senior + mezzanine debt sculpted to min. 1.30x DSCR | Working capital revolver, DSRA & MRA | USD reporting currency
B8: Live Scenario Switcher
B9: Active Scenario (select): | C9: Base | D9: << This single cell drives the entire model (Assumptions, Operations, Debt, Outputs).
B11: Scenario key changes vs Base:
B12: Best: Utilisation +10pts | ICE price +15% | Bean cost -5% | Capex -8% | Interest -0.75% | GHS stable
B13: Worst: Utilisation -15pts | ICE price -20% | Bean cost +15% | Capex +10% | Interest +1.5% | GHS depreciates sharply
B15: Key Outputs Snapshot (active scenario, linked live from Outputs sheet)
B16: Senior Debt at COD ($) | D16: =Outputs!$D$7 -> 1.2653082e+08
B17: Equity at COD ($) | D17: =Outputs!$D$8 -> 67287488
B18: Gearing achieved (%) | D18: =Outputs!$D$9 -> 0.76560595
B19: Equity IRR (%) | D19: =Outputs!$D$13 -> 0
B20: Equity NPV @ discount rate ($) | D20: =Outputs!$D$14 -> -59862784
B21: Equity Multiple (x) | D21: =Outputs!$D$15 -> 0
B22: Minimum DSCR (x) | D22: =Outputs!$D$20 -> -0.10661364
B23: Average DSCR (x) | D23: =Outputs!$D$22 -> 1.0009806
B25: Colour Legend
B26: Amber font / amber fill | D26: Editable input — change here to flex the model
B27: Black font, white fill | D27: Formula calculated within the same sheet
B28: Green font | D28: Link pulled from another sheet
B29: Teal bold font | D29: Key output / positive result
B30: Brown font, amber-warn fill | D30: Check / warning flag — review before signing off
B33: Model built: monthly construction cash-flow, semi-annual operating periods over the 10-year debt tenor.
B34: See 'Audit' sheet for lender-style quality-control checks and 'Glossary' for term definitions.
B37: Table of Content
B38: Assumptions
B39: Timing
B40: Construction
B41: Operations
B42: Waterfall
B43: WorkingCap
B44: Reserves
B45: Outputs
B46: Sensitivities
... B49: Charts

Sheet Assumptions
B2: Assumptions — Base / Best / Worst Case Inputs
B4: Active Scenario: | D4: =Cover!$C$9 -> Base | E4: <<<< Cover | F4: (All 'Active' values below flex automatically with the Cover-sheet switch)
B6: Assumption | C6: Base Case | D6: Best Case | E6: Worst Case | F6: Active | G6: Unit | H6: Notes / Source
B8: 1. Processing Plant & Capacity
B9: Installed capacity | C9: 15000 | D9: 15000 | E9: 15000 | F9: =IF($D$4="Base",C9,IF($D$4="Best",D9,E9)) -> 15000 | G9: MT beans/yr | H9: Fixed nameplate capacity of the Tema grinding plant (not scenario-flexed).
B10: Utilisation — Year 1 | C10: 0.6 | D10: 0.7 | E10: 0.45 | F10: =IF($D$4="Base",C10,IF($D$4="Best",D10,E10)) -> 0.6 | G10: % of capacity | H10: Ramp-up year. Best/Worst flex Base by +/-10 to 15 pts per brief.
B11: Utilisation — Year 2 | C11: 0.8 | D11: 0.9 | E11: 0.65 | F11: =IF($D$4="Base",C11,IF($D$4="Best",D11,E11)) -> 0.8 | G11: % of capacity | H11: Second ramp-up year.
B12: Utilisation — Year 3 onward | C12: 0.95 | D12: 0.98 | E12: 0.8 | F12: =IF($D$4="Base",C12,IF($D$4="Best",D12,E12)) -> 0.95 | G12: % of capacity | H12: Steady-state utilisation for remainder of debt tenor.
B13: Conversion yield (product/bean) | C13: 0.85 | D13: 0.85 | E13: 0.85 | F13: =IF($D$4="Base",C13,IF($D$4="Best",D13,E13)) -> 0.85 | G13: % by weight | H13: User-specified: ~85% of bean input weight converts to saleable product; balance is shell/moisture loss.
B14: Bean-to-product ratio | C14: 1.1764706 | D14: 1.1764706 | E14: 1.1764706 | F14: =IF($D$4="Base",C14,IF($D$4="Best",D14,E14)) -> 1.1764706 | G14: MT bean / MT product | H14: User-specified feedstock intensity (~1/0.85 consistent with 85% yield).
B15: Product mix — Cocoa liquor | C15: 0.4 | D15: 0.4 | E15: 0.4 | F15: =IF($D$4="Base",C15,IF($D$4="Best",D15,E15)) -> 0.4 | G15: % of output | H15: Fixed product slate (not scenario-flexed).
B16: Product mix — Cocoa butter | C16: 0.3 | D16: 0.3 | E16: 0.3 | F16: =IF($D$4="Base",C16,IF($D$4="Best",D16,E16)) -> 0.3 | G16: % of output
B17: Product mix — Cocoa cake/powder | C17: 0.3 | D17: 0.3 | E17: 0.3 | F17: =IF($D$4="Base",C17,IF($D$4="Best",D17,E17)) -> 0.3 | G17: % of output
B19: 2. Product Pricing (USD, ICE Cocoa Benchmark-Linked)
B20: ICE cocoa benchmark price (base, at COD) | C20: 7000 | D20: 8050 | E20: 5600 | F20: =IF($D$4="Base",C20,IF($D$4="Best",D20,E20)) -> 7000 | G20: $/MT | H20: Illustrative base ICE No.2 cocoa futures reference; Best +15%, Worst -20% per brief.
B21: Processing differential — Liquor | C21: 400 | D21: 400 | E21: 400 | F21: =IF($D$4="Base",C21,IF($D$4="Best",D21,E21)) -> 400 | G21: $/MT | H21: Fixed contractual premium/discount to ICE benchmark (editable).
B22: Processing differential — Butter | C22: 1800 | D22: 1800 | E22: 1800 | F22: =IF($D$4="Base",C22,IF($D$4="Best",D22,E22)) -> 1800 | G22: $/MT | H22: Cocoa butter typically trades at the largest premium to bean-equivalent.
B23: Processing differential — Cake/Powder | C23: -300 | D23: -300 | E23: -300 | F23: =IF($D$4="Base",C23,IF($D$4="Best",D23,E23)) -> -300 | G23: $/MT | H23: Cake/powder typically trades at a discount to bean-equivalent.
B24: Contracted (offtake) share of output | C24: 0.8 | D24: 0.8 | E24: 0.8 | F24: =IF($D$4="Base",C24,IF($D$4="Best",D24,E24)) -> 0.8 | G24: % of output | H24: Multi-year offtake agreements with confectionery manufacturers.
B25: Spot export share of output | C25: 0.2 | D25: 0.2 | E25: 0.2 | F25: =IF($D$4="Base",C25,IF($D$4="Best",D25,E25)) -> 0.2 | G25: % of output | H25: Residual volume sold on the spot export market.
B26: Spot differential pass-through factor | C26: 0.5 | D26: 0.5 | E26: 0.5 | F26: =IF($D$4="Base",C26,IF($D$4="Best",D26,E26)) -> 0.5 | G26: % of contract diff. | H26: Spot sales capture only part of the fixed processing differential, reflecting greater ICE-price pass-through/volatility on uncontracted volume.
B28: 3. Bean Procurement (GHS) & FX
B29: COCOBOD producer price (base year) | C29: 3000 | D29: 2850 | E29: 3450 | F29: =IF($D$4="Base",C29,IF($D$4="Best",D29,E29)) -> 3000 | G29: GHS/64kg bag | H29: Best -5%, Worst +15% vs Base per brief.
B30: Producer price annual escalation | C30: 0.12 | D30: 0.06 | E30: 0.18 | F30: =IF($D$4="Base",C30,IF($D$4="Best",D30,E30)) -> 0.12 | G30: % p.a. (GHS nominal) | H30: Nominal GHS escalation is linked to the FX scenario: Best case (stable GHS) assumes materially lower domestic cost inflation (~6%/yr); Worst case (sharp depreciation) assumes higher pass-through domestic inflation (~18%/yr); Base sits at the historical COCOBOD trend (~12%/yr with ~8%/yr GHS depreciation). This reflects the real-world link between a currency's stability and the domestic nominal price inflation it experiences (purchasing-power-parity intuition) -- without this link, a stable-FX Best Case can perversely show weaker USD economics than Base over a 10-year tenor, since nominal GHS cost growth then has no offsetting depreciation benefit.
B31: Bag weight | C31: 64 | D31: 64 | E31: 64 | F31: =IF($D$4="Base",C31,IF($D$4="Best",D31,E31)) -> 64 | G31: kg/bag | H31: Standard COCOBOD bag size.
B32: USD/GHS exchange rate at COD | C32: 13 | D32: 11 | E32: 15 | F32: =IF($D$4="Base",C32,IF($D$4="Best",D32,E32)) -> 13 | G32: GHS per USD | H32: Spot FX at financial close; fixed starting point across scenarios.
B33: Annual GHS depreciation vs USD | C33: 0.05 | D33: 0.01 | E33: 0.1 | F33: =IF($D$4="Base",C33,IF($D$4="Best",D33,E33)) -> 0.05 | G33: % p.a. | H33: Central FX risk driver. Best: GHS holds stable. Worst: sharp depreciation.
B35: 4. Operating Costs (USD)
B36: Plant all-in capex | C36: 12000 | D36: 11040 | E36: 13200 | F36: =IF($D$4="Base",C36,IF($D$4="Best",D36,E36)) -> 12000 | G36: $/MT installed | H36: NOTE ON THIS INPUT: the brief specified $180,000/MT (=$2.7bn total capex for 15,000 MT/yr), which is 1-2 orders of magnitude above observed capex intensity for integrated cocoa liquor/butter/powder plants (industry benchmarks cluster around $3,000-12,000/MT depending on scope and sophistication). At $180,000/MT the resulting debt quantum makes debt service uncoverable by plant cash flow at any realistic price, independent of the O&M assumption. We have used $12,000/MT (~$180m total capex, consistent with the digits in the brief but expressed per the correct order of magnitude) as the working Base Case. This cell is a live amber input -- set it back to 180,000 to reproduce the as-specified stress case.
B37: Annual O&M | C37: 950 | D37: 950 | E37: 950 | F37: =IF($D$4="Base",C37,IF($D$4="Best",D37,E37)) -> 950 | G37: $/MT processed | H37: NOTE ON THIS INPUT: the brief specified $9,500/MT. At that level, O&M alone (~$11,200/MT of product after the 1.18x bean ratio) exceeds achievable product revenue at any realistic ICE cocoa price (recent range ~$3,100-$12,900/MT; 2026 forward curve ~$6,000-6,300/MT), making the plant structurally loss-making and DSCR/IRR undefined regardless of financing structure. This is far above observed cocoa-grinding O&M benchmarks (~$200-500/MT). We have used $950/MT (1/10th of the brief figure) as the working Base Case so the model produces a functioning, bankable result. This cell is a live amber input -- set it back to 9,500 to reproduce the as-specified stress case and observe the resulting covenant breach flagged on the Audit sheet.
B38: Logistics / freight to port & export shipping | C38: 45 | D38: 45 | E38: 45 | F38: =IF($D$4="Base",C38,IF($D$4="Best",D38,E38)) -> 45 | G38: $/MT product | H38: Escalated at USD inflation.
B40: 5. Financing
B41: Debt tenor | C41: 10 | D41: 10 | E41: 10 | F41: =IF($D$4="Base",C41,IF($D$4="Best",D41,E41)) -> 10 | G41: years from COD | H41: Fixed across scenarios.
B42: All-in senior interest rate | C42: 0.095 | D42: 0.0875 | E42: 0.11 | F42: =IF($D$4="Base",C42,IF($D$4="Best",D42,E42)) -> 0.095 | G42: % p.a. | H42: Best -0.75pt, Worst +1.50pt vs Base per brief.
B43: Upfront arrangement fee | C43: 0.015 | D43: 0.015 | E43: 0.015 | F43: =IF($D$4="Base",C43,IF($D$4="Best",D43,E43)) -> 0.015 | G43: % of facility | H43: Charged on committed senior facility; capitalised into debt at COD.
B44: DSRA sizing | C44: 6 | D44: 6 | E44: 6 | F44: =IF($D$4="Base",C44,IF($D$4="Best",D44,E44)) -> 6 | G44: months of debt service | H44: Debt Service Reserve funded at COD, equal to next 6 months (1 semi-annual period) of debt service.
B45: Target minimum DSCR | C45: 1.3 | D45: 1.3 | E45: 1.3 | F45: =IF($D$4="Base",C45,IF($D$4="Best",D45,E45)) -> 1.3 | G45: x | H45: Senior debt sculpted so scheduled debt service never exceeds CFADS / 1.30x.
B46: Target gearing | C46: 0.6 | D46: 0.6 | E46: 0.6 | F46: =IF($D$4="Base",C46,IF($D$4="Best",D46,E46)) -> 0.6 | G46: % debt / total base capex | H46: Senior debt sized at 60% of base plant capex; IDC & fees capitalised on top.
B48: 6. Macro & Tax
B49: USD inflation | C49: 0.022 | D49: 0.022 | E49: 0.022 | F49: =IF($D$4="Base",C49,IF($D$4="Best",D49,E49)) -> 0.022 | G49: % p.a. | H49: Applied to USD-denominated costs and to nominal escalation of ICE price.
B50: Corporate tax rate (Ghana) | C50: 0.25 | D50: 0.25 | E50: 0.25 | F50: =IF($D$4="Base",C50,IF($D$4="Best",D50,E50)) -> 0.25 | G50: % | H50: Standard Ghana corporate income tax rate.
B51: Ghana Free Zone / agro-processing tax holiday | C51: Yes | D51: Yes | E51: No | F51: =IF($D$4="Base",C51,IF($D$4="Best",D51,E51)) -> Yes | G51: Yes/No toggle | H51: If 'Yes': 0% tax during the holiday period below (common concession for export-oriented agro-processors).
B52: Free Zone tax holiday period | C52: 10 | D52: 10 | E52: 10 | F52: =IF($D$4="Base",C52,IF($D$4="Best",D52,E52)) -> 10 | G52: years | H52: Applies from COD; coincides with the debt tenor in this model.
B53: Tax depreciation period (straight-line) | C53: 10 | D53: 10 | E53: 10 | F53: =IF($D$4="Base",C53,IF($D$4="Best",D53,E53)) -> 10 | G53: years | H53: Straight-line depreciation of total installed cost for tax purposes.
B54: Equity discount rate | C54: 0.14 | D54: 0.14 | E54: 0.14 | F54: =IF($D$4="Base",C54,IF($D$4="Best",D54,E54)) -> 0.14 | G54: % p.a. | H54: Used to NPV the equity cash-flow stream.
B56: 7. Timing
B57: Construction start date | C57: 46388 | D57: 46388 | E57: 46388 | F57: =IF($D$4="Base",C57,IF($D$4="Best",D57,E57)) -> 46388 | G57: date | H57: COD minus 18-month construction period.
B58: Construction duration | C58: 18 | D58: 18 | E58: 18 | F58: =IF($D$4="Base",C58,IF($D$4="Best",D58,E58)) -> 18 | G58: months | H58: Fixed EPC programme duration.
B59: Commercial Operation Date (COD) | C59: 46935 | D59: 46935 | E59: 46935 | F59: =IF($D$4="Base",C59,IF($D$4="Best",D59,E59)) -> 46935 | G59: date | H59: Target COD per brief.
B61: 8. Derived — Effective Tax Rate Helper
B62: Effective tax rate applied in Operations = IF(Free Zone="Yes", 0%, Active tax rate) throughout the (10-yr) holiday/tenor window.
B65: 9. Construction Contingency & VAT Financing
B66: Construction contingency | C66: 0.08 | D66: 0.08 | E66: 0.08 | F66: =IF($D$4="Base",C66,IF($D$4="Best",D66,E66)) -> 0.08 | G66: % of base capex | H66: Standard EPC contingency allowance; added to Total Base Capex before gearing is applied.
B67: Ghana import VAT rate on plant & equipment | C67: 0.15 | D67: 0.15 | E67: 0.15 | F67: =IF($D$4="Base",C67,IF($D$4="Best",D67,E67)) -> 0.15 | G67: % | H67: Standard Ghana VAT rate; typically paid upfront on imported equipment and reclaimed via refund post-COD.
B68: VAT bridge facility interest rate | C68: 0.12 | D68: 0.1125 | E68: 0.135 | F68: =IF($D$4="Base",C68,IF($D$4="Best",D68,E68)) -> 0.12 | G68: % p.a. | H68: Short-term facility bridging the VAT cash outlay to refund; priced at a margin above senior debt given short tenor/refund risk.
B69: VAT bridge facility repayment period | C69: 9 | D69: 9 | E69: 9 | F69: =IF($D$4="Base",C69,IF($D$4="Best",D69,E69)) -> 9 | G69: months from COD | H69: Assumed time to receive VAT refund from Ghana Revenue Authority and fully repay the bridge facility.
B70: 10. Maintenance Reserve Account (MRA)
B71: Annual maintenance reserve provision | C71: 150 | D71: 150 | E71: 150 | F71: =IF($D$4="Base",C71,IF($D$4="Best",D71,E71)) -> 150 | G71: $/MT processed | H71: Funded each period into the MRA ahead of periodic major overhauls; escalated at USD inflation.
B72: Major overhaul interval | C72: 5 | D72: 5 | E72: 5 | F72: =IF($D$4="Base",C72,IF($D$4="Best",D72,E72)) -> 5 | G72: years | H72: Assumed frequency of a major planned overhaul of grinding/pressing equipment.
B73: Major overhaul cost | C73: 0.04 | D73: 0.04 | E73: 0.04 | F73: =IF($D$4="Base",C73,IF($D$4="Best",D73,E73)) -> 0.04 | G73: % of base capex | H73: Cost of each major overhaul, drawn from the MRA when due.
B74: 11. Additional Financing Layers — Mezzanine Debt
B75: Mezzanine debt sizing | C75: 0.15 | D75: 0.15 | E75: 0.15 | F75: =IF($D$4="Base",C75,IF($D$4="Best",D75,E75)) -> 0.15 | G75: % of base capex | H75: Subordinated tranche sized on top of senior debt; reduces base-case equity cheque from ~40% to ~25% of base capex.
B76: Mezzanine interest rate (cash-pay) | C76: 0.14 | D76: 0.1325 | E76: 0.155 | F76: =IF($D$4="Base",C76,IF($D$4="Best",D76,E76)) -> 0.14 | G76: % p.a. | H76: Priced at a premium to senior debt for subordination risk; Best/Worst flex by the same +/- delta as senior.
B77: 12. FX Hedging
B78: Bean-cost FX hedge ratio | C78: 0.5 | D78: 0.5 | E78: 0.5 | F78: =IF($D$4="Base",C78,IF($D$4="Best",D78,E78)) -> 0.5 | G78: % of bean cost hedged | H78: Hedge applies to Years 1-2 only (typical corporate FX-hedging horizon for a new project); Year 3 onward is fully unhedged. A rolling hedge held flat at the COD rate for the full 10-year tenor was tested and found to remove the natural offset between GHS producer-price escalation and GHS depreciation, causing bean costs to compound sharply -- an interesting but unrealistic outcome for a decade-long hedge, so the horizon was limited to reflect market practice.
B79: 13. Dividend Withholding Tax
B80: Dividend withholding tax rate | C80: 0.08 | D80: 0.08 | E80: 0.08 | F80: =IF($D$4="Base",C80,IF($D$4="Best",D80,E80)) -> 0.08 | G80: % of gross distribution | H80: Assumed treaty-reduced rate on dividends repatriated to a foreign sponsor (Ghana domestic rate is higher without treaty relief).
B81: 14. Financial Covenants
B82: Maximum leverage covenant (Senior Debt / EBITDA) | C82: 5 | D82: 5 | E82: 5 | F82: =IF($D$4="Base",C82,IF($D$4="Best",D82,E82)) -> 5 | G82: x | H82: Annualised EBITDA (current period x2) vs opening senior debt balance; a REVIEW/FAIL flag if breached.
B83: Minimum liquidity covenant | C83: 2000000 | D83: 2000000 | E83: 2000000 | F83: =IF($D$4="Base",C83,IF($D$4="Best",D83,E83)) -> 2000000 | G83: $ | H83: Minimum combined DSRA + MRA balance required at all times.
B84: Distribution lock-up DSCR trigger | C84: 1.15 | D84: 1.15 | E84: 1.15 | F84: =IF($D$4="Base",C84,IF($D$4="Best",D84,E84)) -> 1.15 | G84: x | H84: If trailing DSCR falls below this trigger, equity distributions are trapped in a cash-trap account until it recovers.
B85: 15. Working Capital & Revolver
B86: Accounts receivable (days sales) | C86: 45 | D86: 45 | E86: 45 | F86: =IF($D$4="Base",C86,IF($D$4="Best",D86,E86)) -> 45 | G86: days | H86: Applied to total product revenue.
B87: Bean inventory (average days of consumption) | C87: 30 | D87: 30 | E87: 30 | F87: =IF($D$4="Base",C87,IF($D$4="Best",D87,E87)) -> 30 | G87: days | H87: Buffer stock of unprocessed beans; seasonally skewed via the H1/H2 factor below.
B88: Finished goods inventory (days of COGS) | C88: 20 | D88: 20 | E88: 20 | F88: =IF($D$4="Base",C88,IF($D$4="Best",D88,E88)) -> 20 | G88: days | H88: Product awaiting shipment/export.
B89: Accounts payable (days of bean cost) | C89: 30 | D89: 30 | E89: 30 | F89: =IF($D$4="Base",C89,IF($D$4="Best",D89,E89)) -> 30 | G89: days | H89: Payment terms with COCOBOD-licensed buying companies.
B90: Working-capital revolver limit | C90: 15000000 | D90: 15000000 | E90: 15000000 | F90: =IF($D$4="Base",C90,IF($D$4="Best",D90,E90)) -> 15000000 | G90: $ | H90: Committed revolving facility funding seasonal working-capital swings ahead of senior debt in the waterfall.
B91: Working-capital revolver interest rate | C91: 0.11 | D91: 0.1025 | E91: 0.125 | F91: =IF($D$4="Base",C91,IF($D$4="Best",D91,E91)) -> 0.11 | G91: % p.a. | H91: Priced at a small margin to senior debt; Best/Worst flex by the same delta as senior.
B92: Seasonal bean-purchase skew — H1 share | C92: 0.6 | D92: 0.6 | E92: 0.6 | F92: =IF($D$4="Base",C92,IF($D$4="Best",D92,E92)) -> 0.6 | G92: % of annual bean volume | H92: Reflects the main crop (Oct-Mar) driving heavier bean procurement/inventory build in the H1 (Jul-Dec) half-year.
B93: 16. Commissioning Ramp-Up Detail (Year 1)
B94: Year 1, H1 utilisation factor (x Year-1 average) | C94: 0.7 | D94: 0.75 | E94: 0.6 | F94: =IF($D$4="Base",C94,IF($D$4="Best",D94,E94)) -> 0.7 | G94: factor | H94: Gradual commissioning: H1 runs below the Year-1 average utilisation.
B95: Year 1, H2 utilisation factor (x Year-1 average) | C95: 1.3 | D95: 1.25 | E95: 1.4 | F95: =IF($D$4="Base",C95,IF($D$4="Best",D95,E95)) -> 1.3 | G95: factor | H95: H2 runs above the Year-1 average to complete the ramp; the two halves average back to the stated Year-1 utilisation.
B96: 17. Offtake Contract Detail
B97: Contracted price floor | C97: 0.85 | D97: 0.85 | E97: 0.85 | F97: =IF($D$4="Base",C97,IF($D$4="Best",D97,E97)) -> 0.85 | G97: % of COD-year contracted price | H97: Protects the offtaker-agreed floor price, escalated at USD inflation, below which the contracted price cannot fall.
B98: Take-or-pay minimum | C98: 0.9 | D98: 0.9 | E98: 0.9 | F98: =IF($D$4="Base",C98,IF($D$4="Best",D98,E98)) -> 0.9 | G98: % of contracted volume | H98: Minimum share of the contracted volume commitment the offtaker must pay for regardless of actual utilisation-driven delivery.
B99: Offtake contract renewal year | C99: 5 | D99: 5 | E99: 5 | F99: =IF($D$4="Base",C99,IF($D$4="Best",D99,E99)) -> 5 | G99: operating year | H99: Multi-year contracts are assumed to renew mid-tenor, at which point the processing differential steps per below.
B100: Differential step at contract renewal | C100: -0.1 | D100: -0.05 | E100: -0.2 | F100: =IF($D$4="Base",C100,IF($D$4="Best",D100,E100)) -> -0.1 | G100: % change to differentials | H100: Reflects renegotiation risk at renewal; applied to all three product differentials from the renewal year onward.
B101: 18. Terminal Value
B102: Exit EV/EBITDA multiple at loan maturity | C102: 5 | D102: 6 | E102: 4 | F102: =IF($D$4="Base",C102,IF($D$4="Best",D102,E102)) -> 5 | G102: x | H102: Applied to annualised final-year EBITDA to estimate a terminal equity value at the end of the debt tenor (going-concern refinancing/sale).
B104: 19. Bean Price / ICE Price Linkage
B105: COCOBOD producer-price sensitivity to ICE price | C105: 0.3 | D105: 0.3 | E105: 0.3 | F105: =IF($D$4="Base",C105,IF($D$4="Best",D105,E105)) -> 0.3 | G105: beta (elasticity) | H105: Partial pass-through: a real (inflation-adjusted) rise/fall in the ICE benchmark relative to its own escalation path nudges the GHS producer price up/down by this fraction, reflecting that COCOBOD price-setting has regard to world prices.

Sheet Timing
B2: Timing & Calendar
B4: Monthly construction programme and semi-annual operating periods, driven off Assumptions dates.
B6: Construction Programme (Month 1 - 18)
B7: Month # | C7: Month Start | D7: Month End | E7: Cum. Months
B8: 1 | C8: =Assumptions!$F$57 -> 46388 | D8: =EDATE(C8,1)-1 -> 46418 | E8: =B8 -> 1
B9: 2 | C9: =EDATE(C8,1) -> 46419 | D9: =EDATE(C9,1)-1 -> 46446 | E9: =B9 -> 2
B10: 3 | C10: =EDATE(C9,1) -> 46447 | D10: =EDATE(C10,1)-1 -> 46477 | E10: =B10 -> 3
B11: 4 | C11: =EDATE(C10,1) -> 46478 | D11: =EDATE(C11,1)-1 -> 46507 | E11: =B11 -> 4
B12: 5 | C12: =EDATE(C11,1) -> 46508 | D12: =EDATE(C12,1)-1 -> 46538 | E12: =B12 -> 5
B13: 6 | C13: =EDATE(C12,1) -> 46539 | D13: =EDATE(C13,1)-1 -> 46568 | E13: =B13 -> 6
B14: 7 | C14: =EDATE(C13,1) -> 46569 | D14: =EDATE(C14,1)-1 -> 46599 | E14: =B14 -> 7
B15: 8 | C15: =EDATE(C14,1) -> 46600 | D15: =EDATE(C15,1)-1 -> 46630 | E15: =B15 -> 8
B16: 9 | C16: =EDATE(C15,1) -> 46631 | D16: =EDATE(C16,1)-1 -> 46660 | E16: =B16 -> 9
B17: 10 | C17: =EDATE(C16,1) -> 46661 | D17: =EDATE(C17,1)-1 -> 46691 | E17: =B17 -> 10
B18: 11 | C18: =EDATE(C17,1) -> 46692 | D18: =EDATE(C18,1)-1 -> 46721 | E18: =B18 -> 11
B19: 12 | C19: =EDATE(C18,1) -> 46722 | D19: =EDATE(C19,1)-1 -> 46752 | E19: =B19 -> 12
B20: 13 | C20: =EDATE(C19,1) -> 46753 | D20: =EDATE(C20,1)-1 -> 46783 | E20: =B20 -> 13
... B25: 18 | C25: =EDATE(C24,1) -> 46905 | D25: =EDATE(C25,1)-1 -> 46934 | E25: =B25 -> 18
B28: Operating Periods (Semi-Annual, 20 periods = 10-yr Debt Tenor)
B29: Period # | C29: Op. Year | D29: Half | E29: Period Start | F29: Period End | G29: t (yrs since COD, midpoint) | H29: Days in period
B30: 1 | C30: =ROUNDUP(B30/2,0) -> 1 | D30: =IF(MOD(B30,2)=1,"H1","H2") -> H1 | E30: =Assumptions!$F$59 -> 46935 | F30: =EDATE(E30,6)-1 -> 47118 | G30: =((B30-1)+0.5)/2 -> 0.25 | H30: =F30-E30+1 -> 184
B31: 2 | C31: =ROUNDUP(B31/2,0) -> 1 | D31: =IF(MOD(B31,2)=1,"H1","H2") -> H2 | E31: =EDATE(E30,6) -> 47119 | F31: =EDATE(E31,6)-1 -> 47299 | G31: =((B31-1)+0.5)/2 -> 0.75 | H31: =F31-E31+1 -> 181
B32: 3 | C32: =ROUNDUP(B32/2,0) -> 2 | D32: =IF(MOD(B32,2)=1,"H1","H2") -> H1 | E32: =EDATE(E31,6) -> 47300 | F32: =EDATE(E32,6)-1 -> 47483 | G32: =((B32-1)+0.5)/2 -> 1.25 | H32: =F32-E32+1 -> 184
B33: 4 | C33: =ROUNDUP(B33/2,0) -> 2 | D33: =IF(MOD(B33,2)=1,"H1","H2") -> H2 | E33: =EDATE(E32,6) -> 47484 | F33: =EDATE(E33,6)-1 -> 47664 | G33: =((B33-1)+0.5)/2 -> 1.75 | H33: =F33-E33+1 -> 181
B34: 5 | C34: =ROUNDUP(B34/2,0) -> 3 | D34: =IF(MOD(B34,2)=1,"H1","H2") -> H1 | E34: =EDATE(E33,6) -> 47665 | F34: =EDATE(E34,6)-1 -> 47848 | G34: =((B34-1)+0.5)/2 -> 2.25 | H34: =F34-E34+1 -> 184
B35: 6 | C35: =ROUNDUP(B35/2,0) -> 3 | D35: =IF(MOD(B35,2)=1,"H1","H2") -> H2 | E35: =EDATE(E34,6) -> 47849 | F35: =EDATE(E35,6)-1 -> 48029 | G35: =((B35-1)+0.5)/2 -> 2.75 | H35: =F35-E35+1 -> 181
B36: 7 | C36: =ROUNDUP(B36/2,0) -> 4 | D36: =IF(MOD(B36,2)=1,"H1","H2") -> H1 | E36: =EDATE(E35,6) -> 48030 | F36: =EDATE(E36,6)-1 -> 48213 | G36: =((B36-1)+0.5)/2 -> 3.25 | H36: =F36-E36+1 -> 184
B37: 8 | C37: =ROUNDUP(B37/2,0) -> 4 | D37: =IF(MOD(B37,2)=1,"H1","H2") -> H2 | E37: =EDATE(E36,6) -> 48214 | F37: =EDATE(E37,6)-1 -> 48395 | G37: =((B37-1)+0.5)/2 -> 3.75 | H37: =F37-E37+1 -> 182
B38: 9 | C38: =ROUNDUP(B38/2,0) -> 5 | D38: =IF(MOD(B38,2)=1,"H1","H2") -> H1 | E38: =EDATE(E37,6) -> 48396 | F38: =EDATE(E38,6)-1 -> 48579 | G38: =((B38-1)+0.5)/2 -> 4.25 | H38: =F38-E38+1 -> 184
B39: 10 | C39: =ROUNDUP(B39/2,0) -> 5 | D39: =IF(MOD(B39,2)=1,"H1","H2") -> H2 | E39: =EDATE(E38,6) -> 48580 | F39: =EDATE(E39,6)-1 -> 48760 | G39: =((B39-1)+0.5)/2 -> 4.75 | H39: =F39-E39+1 -> 181
B40: 11 | C40: =ROUNDUP(B40/2,0) -> 6 | D40: =IF(MOD(B40,2)=1,"H1","H2") -> H1 | E40: =EDATE(E39,6) -> 48761 | F40: =EDATE(E40,6)-1 -> 48944 | G40: =((B40-1)+0.5)/2 -> 5.25 | H40: =F40-E40+1 -> 184
B41: 12 | C41: =ROUNDUP(B41/2,0) -> 6 | D41: =IF(MOD(B41,2)=1,"H1","H2") -> H2 | E41: =EDATE(E40,6) -> 48945 | F41: =EDATE(E41,6)-1 -> 49125 | G41: =((B41-1)+0.5)/2 -> 5.75 | H41: =F41-E41+1 -> 181
B42: 13 | C42: =ROUNDUP(B42/2,0) -> 7 | D42: =IF(MOD(B42,2)=1,"H1","H2") -> H1 | E42: =EDATE(E41,6) -> 49126 | F42: =EDATE(E42,6)-1 -> 49309 | G42: =((B42-1)+0.5)/2 -> 6.25 | H42: =F42-E42+1 -> 184
... B49: 20 | C49: =ROUNDUP(B49/2,0) -> 10 | D49: =IF(MOD(B49,2)=1,"H1","H2") -> H2 | E49: =EDATE(E48,6) -> 50406 | F49: =EDATE(E49,6)-1 -> 50586 | G49: =((B49-1)+0.5)/2 -> 9.75 | H49: =F49-E49+1 -> 181

Sheet Construction
B2: Construction — Capex Drawdown, Funding Split & IDC
B4: Active Scenario: | C4: =Cover!$C$9 -> Base | D4: <<<< Cover
B5: Base Project Cost
B6: Total Base Capex ($) | D6: =Assumptions!$F$9*Assumptions!$F$36*(1+Assumptions!$F$66) -> 194400000 | F6: Installed capacity x Capex/MT x (1+contingency%) -- Active scenario
B8: Monthly Drawdown Schedule (Month 1 - 18)
B9: Month # | C9: Date | D9: Capex Draw % (S-curve input) | E9: Capex Draw $ | F9: Debt Draw $ (Gearing x Capex) | G9: Equity Draw $ | H9: Opening Debt Balance | I9: IDC accrued (capitalised) | J9: Closing Debt Balance | K9: Mezz Draw $ (% of Capex) | L9: Mezz Opening Balance | M9: Mezz IDC accrued (capitalised) | N9: Mezz Closing Balance
B10: =Timing!B8 -> 1 | C10: =Timing!C8 -> 46388 | D10: 0.01 | E10: =D10*$D$6 -> 1944000 | F10: =E10*Assumptions!$F$46 -> 1166400 | G10: =E10-F10-K10 -> 486000 | H10: =IF(B10=1,0,J9) -> 0 | I10: =H10*Assumptions!$F$42/12 -> 0 | J10: =H10+F10+I10 -> 1166400 | K10: =E10*Assumptions!$F$75 -> 291600 | L10: =IF(B10=1,0,N9) -> 0 | M10: =L10*Assumptions!$F$76/12 -> 0 | N10: =L10+K10+M10 -> 291600
B11: =Timing!B9 -> 2 | C11: =Timing!C9 -> 46419 | D11: 0.02 | E11: =D11*$D$6 -> 3888000 | F11: =E11*Assumptions!$F$46 -> 2332800 | G11: =E11-F11-K11 -> 972000 | H11: =IF(B11=1,0,J10) -> 1166400 | I11: =H11*Assumptions!$F$42/12 -> 9234 | J11: =H11+F11+I11 -> 3508434 | K11: =E11*Assumptions!$F$75 -> 583200 | L11: =IF(B11=1,0,N10) -> 291600 | M11: =L11*Assumptions!$F$76/12 -> 3402 | N11: =L11+K11+M11 -> 878202
B12: =Timing!B10 -> 3 | C12: =Timing!C10 -> 46447 | D12: 0.03 | E12: =D12*$D$6 -> 5832000 | F12: =E12*Assumptions!$F$46 -> 3499200 | G12: =E12-F12-K12 -> 1458000 | H12: =IF(B12=1,0,J11) -> 3508434 | I12: =H12*Assumptions!$F$42/12 -> 27775.102 | J12: =H12+F12+I12 -> 7035409.1 | K12: =E12*Assumptions!$F$75 -> 874800 | L12: =IF(B12=1,0,N11) -> 878202 | M12: =L12*Assumptions!$F$76/12 -> 10245.69 | N12: =L12+K12+M12 -> 1763247.7
B13: =Timing!B11 -> 4 | C13: =Timing!C11 -> 46478 | D13: 0.04 | E13: =D13*$D$6 -> 7776000 | F13: =E13*Assumptions!$F$46 -> 4665600 | G13: =E13-F13-K13 -> 1944000 | H13: =IF(B13=1,0,J12) -> 7035409.1 | I13: =H13*Assumptions!$F$42/12 -> 55696.989 | J13: =H13+F13+I13 -> 11756706 | K13: =E13*Assumptions!$F$75 -> 1166400 | L13: =IF(B13=1,0,N12) -> 1763247.7 | M13: =L13*Assumptions!$F$76/12 -> 20571.223 | N13: =L13+K13+M13 -> 2950218.9
B14: =Timing!B12 -> 5 | C14: =Timing!C12 -> 46508 | D14: 0.06 | E14: =D14*$D$6 -> 11664000 | F14: =E14*Assumptions!$F$46 -> 6998400 | G14: =E14-F14-K14 -> 2916000 | H14: =IF(B14=1,0,J13) -> 11756706 | I14: =H14*Assumptions!$F$42/12 -> 93073.923 | J14: =H14+F14+I14 -> 18848180 | K14: =E14*Assumptions!$F$75 -> 1749600 | L14: =IF(B14=1,0,N13) -> 2950218.9 | M14: =L14*Assumptions!$F$76/12 -> 34419.221 | N14: =L14+K14+M14 -> 4734238.1
B15: =Timing!B13 -> 6 | C15: =Timing!C13 -> 46539 | D15: 0.07 | E15: =D15*$D$6 -> 13608000 | F15: =E15*Assumptions!$F$46 -> 8164800 | G15: =E15-F15-K15 -> 3402000 | H15: =IF(B15=1,0,J14) -> 18848180 | I15: =H15*Assumptions!$F$42/12 -> 149214.76 | J15: =H15+F15+I15 -> 27162195 | K15: =E15*Assumptions!$F$75 -> 2041200 | L15: =IF(B15=1,0,N14) -> 4734238.1 | M15: =L15*Assumptions!$F$76/12 -> 55232.778 | N15: =L15+K15+M15 -> 6830670.9
B16: =Timing!B14 -> 7 | C16: =Timing!C14 -> 46569 | D16: 0.08 | E16: =D16*$D$6 -> 15552000 | F16: =E16*Assumptions!$F$46 -> 9331200 | G16: =E16-F16-K16 -> 3888000 | H16: =IF(B16=1,0,J15) -> 27162195 | I16: =H16*Assumptions!$F$42/12 -> 215034.04 | J16: =H16+F16+I16 -> 36708429 | K16: =E16*Assumptions!$F$75 -> 2332800 | L16: =IF(B16=1,0,N15) -> 6830670.9 | M16: =L16*Assumptions!$F$76/12 -> 79691.161 | N16: =L16+K16+M16 -> 9243162.1
B17: =Timing!B15 -> 8 | C17: =Timing!C15 -> 46600 | D17: 0.09 | E17: =D17*$D$6 -> 17496000 | F17: =E17*Assumptions!$F$46 -> 10497600 | G17: =E17-F17-K17 -> 4374000 | H17: =IF(B17=1,0,J16) -> 36708429 | I17: =H17*Assumptions!$F$42/12 -> 290608.39 | J17: =H17+F17+I17 -> 47496637 | K17: =E17*Assumptions!$F$75 -> 2624400 | L17: =IF(B17=1,0,N16) -> 9243162.1 | M17: =L17*Assumptions!$F$76/12 -> 107836.89 | N17: =L17+K17+M17 -> 11975399
B18: =Timing!B16 -> 9 | C18: =Timing!C16 -> 46631 | D18: 0.1 | E18: =D18*$D$6 -> 19440000 | F18: =E18*Assumptions!$F$46 -> 11664000 | G18: =E18-F18-K18 -> 4860000 | H18: =IF(B18=1,0,J17) -> 47496637 | I18: =H18*Assumptions!$F$42/12 -> 376015.04 | J18: =H18+F18+I18 -> 59536652 | K18: =E18*Assumptions!$F$75 -> 2916000 | L18: =IF(B18=1,0,N17) -> 11975399 | M18: =L18*Assumptions!$F$76/12 -> 139712.99 | N18: =L18+K18+M18 -> 15031112
B19: =Timing!B17 -> 10 | C19: =Timing!C17 -> 46661 | D19: 0.1 | E19: =D19*$D$6 -> 19440000 | F19: =E19*Assumptions!$F$46 -> 11664000 | G19: =E19-F19-K19 -> 4860000 | H19: =IF(B19=1,0,J18) -> 59536652 | I19: =H19*Assumptions!$F$42/12 -> 471331.83 | J19: =H19+F19+I19 -> 71671984 | K19: =E19*Assumptions!$F$75 -> 2916000 | L19: =IF(B19=1,0,N18) -> 15031112 | M19: =L19*Assumptions!$F$76/12 -> 175362.97 | N19: =L19+K19+M19 -> 18122475
B20: =Timing!B18 -> 11 | C20: =Timing!C18 -> 46692 | D20: 0.09 | E20: =D20*$D$6 -> 17496000 | F20: =E20*Assumptions!$F$46 -> 10497600 | G20: =E20-F20-K20 -> 4374000 | H20: =IF(B20=1,0,J19) -> 71671984 | I20: =H20*Assumptions!$F$42/12 -> 567403.21 | J20: =H20+F20+I20 -> 82736987 | K20: =E20*Assumptions!$F$75 -> 2624400 | L20: =IF(B20=1,0,N19) -> 18122475 | M20: =L20*Assumptions!$F$76/12 -> 211428.87 | N20: =L20+K20+M20 -> 20958304
B21: =Timing!B19 -> 12 | C21: =Timing!C19 -> 46722 | D21: 0.08 | E21: =D21*$D$6 -> 15552000 | F21: =E21*Assumptions!$F$46 -> 9331200 | G21: =E21-F21-K21 -> 3888000 | H21: =IF(B21=1,0,J20) -> 82736987 | I21: =H21*Assumptions!$F$42/12 -> 655001.15 | J21: =H21+F21+I21 -> 92723188 | K21: =E21*Assumptions!$F$75 -> 2332800 | L21: =IF(B21=1,0,N20) -> 20958304 | M21: =L21*Assumptions!$F$76/12 -> 244513.54 | N21: =L21+K21+M21 -> 23535617
... B27: =Timing!B25 -> 18 | C27: =Timing!C25 -> 46905 | D27: 0.01 | E27: =D27*$D$6 -> 1944000 | F27: =E27*Assumptions!$F$46 -> 1166400 | G27: =E27-F27-K27 -> 486000 | H27: =IF(B27=1,0,J26) -> 1.2264389e+08 | I27: =H27*Assumptions!$F$42/12 -> 970930.82 | J27: =H27+F27+I27 -> 1.2478122e+08 | K27: =E27*Assumptions!$F$75 -> 291600 | L27: =IF(B27=1,0,N26) -> 31552609 | M27: =L27*Assumptions!$F$76/12 -> 368113.77 | N27: =L27+K27+M27 -> 32212323
B29: TOTAL | D29: =SUM(D10:D27) -> 1 | E29: =SUM(E10:E27) -> 194400000 | F29: =SUM(F10:F27) -> 116640000 | G29: =SUM(G10:G27) -> 48600000 | I29: =SUM(I10:I27) -> 8141223.3 | K29: =SUM(K10:K27) -> 29160000 | M29: =SUM(M10:M27) -> 3052322.6
B31: Sources & Uses at COD
B32: USES
B33: Base Plant Capex | D33: =E29 -> 194400000
B34: Capitalised Interest During Construction (IDC) | D34: =I29 -> 8141223.3
B35: Upfront Arrangement Fee (capitalised) | D35: =D45 -> 1749600
B36: DSRA Funding at COD | D36: =Reserves!$C$9 -> 18687488
B37: TOTAL USES | D37: =SUM(D33:D36) -> 2.2297831e+08
B39: SOURCES
B40: Senior Debt at COD (draws + capitalised IDC + fee) | D40: =D46 -> 1.2653082e+08
B41: Base Equity Draws (construction period) | D41: =G29 -> 48600000
B42: Additional Equity — DSRA Funding | D42: =Reserves!$C$9 -> 18687488
B43: TOTAL SOURCES | D43: =SUM(D40:D42) -> 1.9381831e+08
B45: Upfront Fee (% of debt draws, capitalised) | D45: =F29*Assumptions!$F$43 -> 1749600
B46: Total Debt at COD (draws + capitalised IDC + fee) | D46: =F29+I29+D45 -> 1.2653082e+08
B47: Achieved gearing at COD (Debt / (Debt+Base Equity)) | D47: =D46/(D46+G29) -> 0.72249317
B49: Sources minus Uses check (must = 0) | D49: =D43-D37+D53 -> 0
B52: Capitalised Interest During Construction — Mezzanine | D52: =M29 -> 3052322.6
B53: VAT Bridge Amount (import VAT on capex, self-funding) | D53: =E29*Assumptions!$F$67 -> 29160000
B54: TOTAL USES (incl. mezzanine IDC & VAT bridge) | D54: =D37+D52+D53 -> 2.5519063e+08
B56: Mezzanine Debt at COD (draws + capitalised interest) | D56: =K29+M29 -> 32212323
B57: VAT Bridge Facility (financing source, self-funding) | D57: =D53 -> 29160000
B58: TOTAL SOURCES (incl. mezzanine & VAT bridge) | D58: =D43+D56+D57 -> 2.5519063e+08
B60: Sources minus Uses check, full structure (must = 0) | D60: =D58-D54 -> 0
B62: Senior gearing only (Senior Debt / (Senior Debt + Base Equity)) | D62: =D46/(D46+G29) -> 0.72249317
B63: Total leverage (Senior + Mezz) / (Senior + Mezz + Base Equity) | D63: =(D46+D56)/(D46+D56+G29) -> 0.76560595

Sheet Operations
B2: Operations — Plant, Bean Procurement (GHS) & Product Sales (USD)
B4: 20 semi-annual periods (Year 1 = periods 1-2, ... Year 10 = periods 19-20). All prices/costs escalate from COD using period-midpoint 't'.
B5: Active Scenario: | C5: =Cover!$C$9 -> Base | D5: <<<< Cover
B6: Timing
B7: Period # | C7: 1 | D7: 2 | E7: 3 | F7: 4 | G7: 5 | H7: 6 | I7: 7 | J7: 8 | K7: 9 | L7: 10 | M7: 11 | N7: 12 | O7: 13 | P7: 14 | Q7: 15 | R7: 16 | S7: 17 | T7: 18 | U7: 19 | V7: 20
B8: Operating Year | C8: =Timing!C30 -> 1 | D8: =Timing!C31 -> 1 | E8: =Timing!C32 -> 2 | F8: =Timing!C33 -> 2 | G8: =Timing!C34 -> 3 | H8: =Timing!C35 -> 3 | I8: =Timing!C36 -> 4 | J8: =Timing!C37 -> 4 | K8: =Timing!C38 -> 5 | L8: =Timing!C39 -> 5 | M8: =Timing!C40 -> 6 | N8: =Timing!C41 -> 6 | O8: =Timing!C42 -> 7 | P8: =Timing!C43 -> 7 | Q8: =Timing!C44 -> 8 | R8: =Timing!C45 -> 8 | S8: =Timing!C46 -> 9 | T8: =Timing!C47 -> 9 | U8: =Timing!C48 -> 10 | V8: =Timing!C49 -> 10
B9: Half | C9: =Timing!D30 -> H1 | D9: =Timing!D31 -> H2 | E9: =Timing!D32 -> H1 | F9: =Timing!D33 -> H2 | G9: =Timing!D34 -> H1 | H9: =Timing!D35 -> H2 | I9: =Timing!D36 -> H1 | J9: =Timing!D37 -> H2 | K9: =Timing!D38 -> H1 | L9: =Timing!D39 -> H2 | M9: =Timing!D40 -> H1 | N9: =Timing!D41 -> H2 | O9: =Timing!D42 -> H1 | P9: =Timing!D43 -> H2 | Q9: =Timing!D44 -> H1 | R9: =Timing!D45 -> H2 | S9: =Timing!D46 -> H1 | T9: =Timing!D47 -> H2 | U9: =Timing!D48 -> H1 | V9: =Timing!D49 -> H2
B10: t (yrs since COD, midpoint) | C10: =Timing!G30 -> 0.25 | D10: =Timing!G31 -> 0.75 | E10: =Timing!G32 -> 1.25 | F10: =Timing!G33 -> 1.75 | G10: =Timing!G34 -> 2.25 | H10: =Timing!G35 -> 2.75 | I10: =Timing!G36 -> 3.25 | J10: =Timing!G37 -> 3.75 | K10: =Timing!G38 -> 4.25 | L10: =Timing!G39 -> 4.75 | M10: =Timing!G40 -> 5.25 | N10: =Timing!G41 -> 5.75 | O10: =Timing!G42 -> 6.25 | P10: =Timing!G43 -> 6.75 | Q10: =Timing!G44 -> 7.25 | R10: =Timing!G45 -> 7.75 | S10: =Timing!G46 -> 8.25 | T10: =Timing!G47 -> 8.75 | U10: =Timing!G48 -> 9.25 | V10: =Timing!G49 -> 9.75
B11: Plant Throughput
B12: Utilisation (% of installed capacity) | C12: =IF(C8=1,Assumptions!$F$10*IF(C9="H1",Assumptions!$F$94,Assumptions!$F$95),IF(C8=2,Assumptions!$F$11,Assumptions!$F$12)) -> 0.42 | D12: =IF(D8=1,Assumptions!$F$10*IF(D9="H1",Assumptions!$F$94,Assumptions!$F$95),IF(D8=2,Assumptions!$F$11,Assumptions!$F$12)) -> 0.78 | E12: =IF(E8=1,Assumptions!$F$10*IF(E9="H1",Assumptions!$F$94,Assumptions!$F$95),IF(E8=2,Assumptions!$F$11,Assumptions!$F$12)) -> 0.8 | F12: =IF(F8=1,Assumptions!$F$10*IF(F9="H1",Assumptions!$F$94,Assumptions!$F$95),IF(F8=2,Assumptions!$F$11,Assumptions!$F$12)) -> 0.8 | G12: =IF(G8=1,Assumptions!$F$10*IF(G9="H1",Assumptions!$F$94,Assumptions!$F$95),IF(G8=2,Assumptions!$F$11,Assumptions!$F$12)) -> 0.95 | H12: =IF(H8=1,Assumptions!$F$10*IF(H9="H1",Assumptions!$F$94,Assumptions!$F$95),IF(H8=2,Assumptions!$F$11,Assumptions!$F$12)) -> 0.95 | I12: =IF(I8=1,Assumptions!$F$10*IF(I9="H1",Assumptions!$F$94,Assumptions!$F$95),IF(I8=2,Assumptions!$F$11,Assumptions!$F$12)) -> 0.95 | J12: =IF(J8=1,Assumptions!$F$10*IF(J9="H1",Assumptions!$F$94,Assumptions!$F$95),IF(J8=2,Assumptions!$F$11,Assumptions!$F$12)) -> 0.95 | ... V12: =IF(V8=1,Assumptions!$F$10*IF(V9="H1",Assumptions!$F$94,Assumptions!$F$95),IF(V8=2,Assumptions!$F$11,Assumptions!$F$12)) -> 0.95
B13: Beans processed (MT) | C13: =C12*Assumptions!$F$9/2 -> 3150 | D13: =D12*Assumptions!$F$9/2 -> 5850 | E13: =E12*Assumptions!$F$9/2 -> 6000 | F13: =F12*Assumptions!$F$9/2 -> 6000 | G13: =G12*Assumptions!$F$9/2 -> 7125 | H13: =H12*Assumptions!$F$9/2 -> 7125 | I13: =I12*Assumptions!$F$9/2 -> 7125 | J13: =J12*Assumptions!$F$9/2 -> 7125 | ... V13: =V12*Assumptions!$F$9/2 -> 7125
B14: Total product output (MT) | C14: =C13*Assumptions!$F$13 -> 2677.5 | D14: =D13*Assumptions!$F$13 -> 4972.5 | E14: =E13*Assumptions!$F$13 -> 5100 | F14: =F13*Assumptions!$F$13 -> 5100 | G14: =G13*Assumptions!$F$13 -> 6056.25 | H14: =H13*Assumptions!$F$13 -> 6056.25 | I14: =I13*Assumptions!$F$13 -> 6056.25 | J14: =J13*Assumptions!$F$13 -> 6056.25 | ... V14: =V13*Assumptions!$F$13 -> 6056.25
B15: Cocoa liquor output (MT) | C15: =C14*Assumptions!$F$15 -> 1071 | D15: =D14*Assumptions!$F$15 -> 1989 | E15: =E14*Assumptions!$F$15 -> 2040 | F15: =F14*Assumptions!$F$15 -> 2040 | G15: =G14*Assumptions!$F$15 -> 2422.5 | H15: =H14*Assumptions!$F$15 -> 2422.5 | I15: =I14*Assumptions!$F$15 -> 2422.5 | J15: =J14*Assumptions!$F$15 -> 2422.5 | ... V15: =V14*Assumptions!$F$15 -> 2422.5
B16: Cocoa butter output (MT) | C16: =C14*Assumptions!$F$16 -> 803.25 | D16: =D14*Assumptions!$F$16 -> 1491.75 | E16: =E14*Assumptions!$F$16 -> 1530 | F16: =F14*Assumptions!$F$16 -> 1530 | G16: =G14*Assumptions!$F$16 -> 1816.875 | H16: =H14*Assumptions!$F$16 -> 1816.875 | I16: =I14*Assumptions!$F$16 -> 1816.875 | J16: =J14*Assumptions!$F$16 -> 1816.875 | ... V16: =V14*Assumptions!$F$16 -> 1816.875
B17: Cocoa cake/powder output (MT) | C17: =C14*Assumptions!$F$17 -> 803.25 | D17: =D14*Assumptions!$F$17 -> 1491.75 | E17: =E14*Assumptions!$F$17 -> 1530 | F17: =F14*Assumptions!$F$17 -> 1530 | G17: =G14*Assumptions!$F$17 -> 1816.875 | H17: =H14*Assumptions!$F$17 -> 1816.875 | I17: =I14*Assumptions!$F$17 -> 1816.875 | J17: =J14*Assumptions!$F$17 -> 1816.875 | ... V17: =V14*Assumptions!$F$17 -> 1816.875
B18: Product Pricing & Revenue (USD, ICE-Linked)
B19: ICE cocoa benchmark price (t) ($/MT) | C19: =Assumptions!$F$20*(1+Assumptions!$F$49)^C10 -> 7038.1864 | D19: =Assumptions!$F$20*(1+Assumptions!$F$49)^D10 -> 7115.1853 | E19: =Assumptions!$F$20*(1+Assumptions!$F$49)^E10 -> 7193.0265 | F19: =Assumptions!$F$20*(1+Assumptions!$F$49)^F10 -> 7271.7193 | G19: =Assumptions!$F$20*(1+Assumptions!$F$49)^G10 -> 7351.2731 | H19: =Assumptions!$F$20*(1+Assumptions!$F$49)^H10 -> 7431.6972 | I19: =Assumptions!$F$20*(1+Assumptions!$F$49)^I10 -> 7513.0011 | J19: =Assumptions!$F$20*(1+Assumptions!$F$49)^J10 -> 7595.1945 | ... V19: =Assumptions!$F$20*(1+Assumptions!$F$49)^V10 -> 8654.5457
B20: Liquor price - contracted ($/MT) | C20: =MAX((Assumptions!$F$97*(Assumptions!$F$20+Assumptions!$F$21)*(1+Assumptions!$F$49)^C10),C19+(Assumptions!$F$21*(1+IF(C8>=Assumptions!$F$99,Assumptions!$F$100,0)))) -> 7438.1864 | D20: =MAX((Assumptions!$F$97*(Assumptions!$F$20+Assumptions!$F$21)*(1+Assumptions!$F$49)^D10),D19+(Assumptions!$F$21*(1+IF(D8>=Assumptions!$F$99,Assumptions!$F$100,0)))) -> 7515.1853 | E20: =MAX((Assumptions!$F$97*(Assumptions!$F$20+Assumptions!$F$21)*(1+Assumptions!$F$49)^E10),E19+(Assumptions!$F$21*(1+IF(E8>=Assumptions!$F$99,Assumptions!$F$100,0)))) -> 7593.0265 | F20: =MAX((Assumptions!$F$97*(Assumptions!$F$20+Assumptions!$F$21)*(1+Assumptions!$F$49)^F10),F19+(Assumptions!$F$21*(1+IF(F8>=Assumptions!$F$99,Assumptions!$F$100,0)))) -> 7671.7193 | G20: =MAX((Assumptions!$F$97*(Assumptions!$F$20+Assumptions!$F$21)*(1+Assumptions!$F$49)^G10),G19+(Assumptions!$F$21*(1+IF(G8>=Assumptions!$F$99,Assumptions!$F$100,0)))) -> 7751.2731 | H20: =MAX((Assumptions!$F$97*(Assumptions!$F$20+Assumptions!$F$21)*(1+Assumptions!$F$49)^H10),H19+(Assumptions!$F$21*(1+IF(H8>=Assumptions!$F$99,Assumptions!$F$100,0)))) -> 7831.6972 | I20: =MAX((Assumptions!$F$97*(Assumptions!$F$20+Assumptions!$F$21)*(1+Assumptions!$F$49)^I10),I19+(Assumptions!$F$21*(1+IF(I8>=Assumptions!$F$99,Assumptions!$F$100,0)))) -> 7913.0011 | J20: =MAX((Assumptions!$F$97*(Assumptions!$F$20+Assumptions!$F$21)*(1+Assumptions!$F$49)^J10),J19+(Assumptions!$F$21*(1+IF(J8>=Assumptions!$F$99,Assumptions!$F$100,0)))) -> 7995.1945 | ... V20: =MAX((Assumptions!$F$97*(Assumptions!$F$20+Assumptions!$F$21)*(1+Assumptions!$F$49)^V10),V19+(Assumptions!$F$21*(1+IF(V8>=Assumptions!$F$99,Assumptions!$F$100,0)))) -> 9014.5457
B21: Liquor price - spot ($/MT) | C21: =C19+Assumptions!$F$21*Assumptions!$F$26 -> 7238.1864 | D21: =D19+Assumptions!$F$21*Assumptions!$F$26 -> 7315.1853 | E21: =E19+Assumptions!$F$21*Assumptions!$F$26 -> 7393.0265 | F21: =F19+Assumptions!$F$21*Assumptions!$F$26 -> 7471.7193 | G21: =G19+Assumptions!$F$21*Assumptions!$F$26 -> 7551.2731 | H21: =H19+Assumptions!$F$21*Assumptions!$F$26 -> 7631.6972 | I21: =I19+Assumptions!$F$21*Assumptions!$F$26 -> 7713.0011 | J21: =J19+Assumptions!$F$21*Assumptions!$F$26 -> 7795.1945 | ... V21: =V19+Assumptions!$F$21*Assumptions!$F$26 -> 8854.5457
B22: Butter price - contracted ($/MT) | C22: =MAX((Assumptions!$F$97*(Assumptions!$F$20+Assumptions!$F$22)*(1+Assumptions!$F$49)^C10),C19+(Assumptions!$F$22*(1+IF(C8>=Assumptions!$F$99,Assumptions!$F$100,0)))) -> 8838.1864 | D22: =MAX((Assumptions!$F$97*(Assumptions!$F$20+Assumptions!$F$22)*(1+Assumptions!$F$49)^D10),D19+(Assumptions!$F$22*(1+IF(D8>=Assumptions!$F$99,Assumptions!$F$100,0)))) -> 8915.1853 | E22: =MAX((Assumptions!$F$97*(Assumptions!$F$20+Assumptions!$F$22)*(1+Assumptions!$F$49)^E10),E19+(Assumptions!$F$22*(1+IF(E8>=Assumptions!$F$99,Assumptions!$F$100,0)))) -> 8993.0265 | F22: =MAX((Assumptions!$F$97*(Assumptions!$F$20+Assumptions!$F$22)*(1+Assumptions!$F$49)^F10),F19+(Assumptions!$F$22*(1+IF(F8>=Assumptions!$F$99,Assumptions!$F$100,0)))) -> 9071.7193 | G22: =MAX((Assumptions!$F$97*(Assumptions!$F$20+Assumptions!$F$22)*(1+Assumptions!$F$49)^G10),G19+(Assumptions!$F$22*(1+IF(G8>=Assumptions!$F$99,Assumptions!$F$100,0)))) -> 9151.2731 | H22: =MAX((Assumptions!$F$97*(Assumptions!$F$20+Assumptions!$F$22)*(1+Assumptions!$F$49)^H10),H19+(Assumptions!$F$22*(1+IF(H8>=Assumptions!$F$99,Assumptions!$F$100,0)))) -> 9231.6972 | I22: =MAX((Assumptions!$F$97*(Assumptions!$F$20+Assumptions!$F$22)*(1+Assumptions!$F$49)^I10),I19+(Assumptions!$F$22*(1+IF(I8>=Assumptions!$F$99,Assumptions!$F$100,0)))) -> 9313.0011 | J22: =MAX((Assumptions!$F$97*(Assumptions!$F$20+Assumptions!$F$22)*(1+Assumptions!$F$49)^J10),J19+(Assumptions!$F$22*(1+IF(J8>=Assumptions!$F$99,Assumptions!$F$100,0)))) -> 9395.1945 | ... V22: =MAX((Assumptions!$F$97*(Assumptions!$F$20+Assumptions!$F$22)*(1+Assumptions!$F$49)^V10),V19+(Assumptions!$F$22*(1+IF(V8>=Assumptions!$F$99,Assumptions!$F$100,0)))) -> 10274.546
B23: Butter price - spot ($/MT) | C23: =C19+Assumptions!$F$22*Assumptions!$F$26 -> 7938.1864 | D23: =D19+Assumptions!$F$22*Assumptions!$F$26 -> 8015.1853 | E23: =E19+Assumptions!$F$22*Assumptions!$F$26 -> 8093.0265 | F23: =F19+Assumptions!$F$22*Assumptions!$F$26 -> 8171.7193 | G23: =G19+Assumptions!$F$22*Assumptions!$F$26 -> 8251.2731 | H23: =H19+Assumptions!$F$22*Assumptions!$F$26 -> 8331.6972 | I23: =I19+Assumptions!$F$22*Assumptions!$F$26 -> 8413.0011 | J23: =J19+Assumptions!$F$22*Assumptions!$F$26 -> 8495.1945 | ... V23: =V19+Assumptions!$F$22*Assumptions!$F$26 -> 9554.5457
B24: Cake/powder price - contracted ($/MT) | C24: =MAX((Assumptions!$F$97*(Assumptions!$F$20+Assumptions!$F$23)*(1+Assumptions!$F$49)^C10),C19+(Assumptions!$F$23*(1+IF(C8>=Assumptions!$F$99,Assumptions!$F$100,0)))) -> 6738.1864 | D24: =MAX((Assumptions!$F$97*(Assumptions!$F$20+Assumptions!$F$23)*(1+Assumptions!$F$49)^D10),D19+(Assumptions!$F$23*(1+IF(D8>=Assumptions!$F$99,Assumptions!$F$100,0)))) -> 6815.1853 | E24: =MAX((Assumptions!$F$97*(Assumptions!$F$20+Assumptions!$F$23)*(1+Assumptions!$F$49)^E10),E19+(Assumptions!$F$23*(1+IF(E8>=Assumptions!$F$99,Assumptions!$F$100,0)))) -> 6893.0265 | F24: =MAX((Assumptions!$F$97*(Assumptions!$F$20+Assumptions!$F$23)*(1+Assumptions!$F$49)^F10),F19+(Assumptions!$F$23*(1+IF(F8>=Assumptions!$F$99,Assumptions!$F$100,0)))) -> 6971.7193 | G24: =MAX((Assumptions!$F$97*(Assumptions!$F$20+Assumptions!$F$23)*(1+Assumptions!$F$49)^G10),G19+(Assumptions!$F$23*(1+IF(G8>=Assumptions!$F$99,Assumptions!$F$100,0)))) -> 7051.2731 | H24: =MAX((Assumptions!$F$97*(Assumptions!$F$20+Assumptions!$F$23)*(1+Assumptions!$F$49)^H10),H19+(Assumptions!$F$23*(1+IF(H8>=Assumptions!$F$99,Assumptions!$F$100,0)))) -> 7131.6972 | I24: =MAX((Assumptions!$F$97*(Assumptions!$F$20+Assumptions!$F$23)*(1+Assumptions!$F$49)^I10),I19+(Assumptions!$F$23*(1+IF(I8>=Assumptions!$F$99,Assumptions!$F$100,0)))) -> 7213.0011 | J24: =MAX((Assumptions!$F$97*(Assumptions!$F$20+Assumptions!$F$23)*(1+Assumptions!$F$49)^J10),J19+(Assumptions!$F$23*(1+IF(J8>=Assumptions!$F$99,Assumptions!$F$100,0)))) -> 7295.1945 | ... V24: =MAX((Assumptions!$F$97*(Assumptions!$F$20+Assumptions!$F$23)*(1+Assumptions!$F$49)^V10),V19+(Assumptions!$F$23*(1+IF(V8>=Assumptions!$F$99,Assumptions!$F$100,0)))) -> 8384.5457
B25: Cake/powder price - spot ($/MT) | C25: =C19+Assumptions!$F$23*Assumptions!$F$26 -> 6888.1864 | D25: =D19+Assumptions!$F$23*Assumptions!$F$26 -> 6965.1853 | E25: =E19+Assumptions!$F$23*Assumptions!$F$26 -> 7043.0265 | F25: =F19+Assumptions!$F$23*Assumptions!$F$26 -> 7121.7193 | G25: =G19+Assumptions!$F$23*Assumptions!$F$26 -> 7201.2731 | H25: =H19+Assumptions!$F$23*Assumptions!$F$26 -> 7281.6972 | I25: =I19+Assumptions!$F$23*Assumptions!$F$26 -> 7363.0011 | J25: =J19+Assumptions!$F$23*Assumptions!$F$26 -> 7445.1945 | ... V25: =V19+Assumptions!$F$23*Assumptions!$F$26 -> 8504.5457
B26: Liquor revenue ($) | C26: =(MAX((C15*Assumptions!$F$24),((Assumptions!$F$9/2*Assumptions!$F$13)*Assumptions!$F$15*Assumptions!$F$24*Assumptions!$F$98)))*C20+((C15*Assumptions!$F$25))*C21 -> 15206930 | D26: =(MAX((D15*Assumptions!$F$24),((Assumptions!$F$9/2*Assumptions!$F$13)*Assumptions!$F$15*Assumptions!$F$24*Assumptions!$F$98)))*D20+((D15*Assumptions!$F$25))*D21 -> 16707861 | E26: =(MAX((E15*Assumptions!$F$24),((Assumptions!$F$9/2*Assumptions!$F$13)*Assumptions!$F$15*Assumptions!$F$24*Assumptions!$F$98)))*E20+((E15*Assumptions!$F$25))*E21 -> 16957151 | F26: =(MAX((F15*Assumptions!$F$24),((Assumptions!$F$9/2*Assumptions!$F$13)*Assumptions!$F$15*Assumptions!$F$24*Assumptions!$F$98)))*F20+((F15*Assumptions!$F$25))*F21 -> 17133738 | G26: =(MAX((G15*Assumptions!$F$24),((Assumptions!$F$9/2*Assumptions!$F$13)*Assumptions!$F$15*Assumptions!$F$24*Assumptions!$F$98)))*G20+((G15*Assumptions!$F$25))*G21 -> 18680559 | H26: =(MAX((H15*Assumptions!$F$24),((Assumptions!$F$9/2*Assumptions!$F$13)*Assumptions!$F$15*Assumptions!$F$24*Assumptions!$F$98)))*H20+((H15*Assumptions!$F$25))*H21 -> 18875386 | I26: =(MAX((I15*Assumptions!$F$24),((Assumptions!$F$9/2*Assumptions!$F$13)*Assumptions!$F$15*Assumptions!$F$24*Assumptions!$F$98)))*I20+((I15*Assumptions!$F$25))*I21 -> 19072345 | J26: =(MAX((J15*Assumptions!$F$24),((Assumptions!$F$9/2*Assumptions!$F$13)*Assumptions!$F$15*Assumptions!$F$24*Assumptions!$F$98)))*J20+((J15*Assumptions!$F$25))*J21 -> 19271459 | ... V26: =(MAX((V15*Assumptions!$F$24),((Assumptions!$F$9/2*Assumptions!$F$13)*Assumptions!$F$15*Assumptions!$F$24*Assumptions!$F$98)))*V20+((V15*Assumptions!$F$25))*V21 -> 21760217
B27: Butter revenue ($) | C27: =(MAX((C16*Assumptions!$F$24),((Assumptions!$F$9/2*Assumptions!$F$13)*Assumptions!$F$16*Assumptions!$F$24*Assumptions!$F$98)))*C22+((C16*Assumptions!$F$25))*C23 -> 13445452 | D27: =(MAX((D16*Assumptions!$F$24),((Assumptions!$F$9/2*Assumptions!$F$13)*Assumptions!$F$16*Assumptions!$F$24*Assumptions!$F$98)))*D22+((D16*Assumptions!$F$25))*D23 -> 14667541 | E27: =(MAX((E16*Assumptions!$F$24),((Assumptions!$F$9/2*Assumptions!$F$13)*Assumptions!$F$16*Assumptions!$F$24*Assumptions!$F$98)))*E22+((E16*Assumptions!$F$25))*E23 -> 14859864 | F27: =(MAX((F16*Assumptions!$F$24),((Assumptions!$F$9/2*Assumptions!$F$13)*Assumptions!$F$16*Assumptions!$F$24*Assumptions!$F$98)))*F22+((F16*Assumptions!$F$25))*F23 -> 14992304 | G27: =(MAX((G16*Assumptions!$F$24),((Assumptions!$F$9/2*Assumptions!$F$13)*Assumptions!$F$16*Assumptions!$F$24*Assumptions!$F$98)))*G22+((G16*Assumptions!$F$25))*G23 -> 16299682 | H27: =(MAX((H16*Assumptions!$F$24),((Assumptions!$F$9/2*Assumptions!$F$13)*Assumptions!$F$16*Assumptions!$F$24*Assumptions!$F$98)))*H22+((H16*Assumptions!$F$25))*H23 -> 16445802 | I27: =(MAX((I16*Assumptions!$F$24),((Assumptions!$F$9/2*Assumptions!$F$13)*Assumptions!$F$16*Assumptions!$F$24*Assumptions!$F$98)))*I22+((I16*Assumptions!$F$25))*I23 -> 16593521 | J27: =(MAX((J16*Assumptions!$F$24),((Assumptions!$F$9/2*Assumptions!$F$13)*Assumptions!$F$16*Assumptions!$F$24*Assumptions!$F$98)))*J22+((J16*Assumptions!$F$25))*J23 -> 16742856 | ... V27: =(MAX((V16*Assumptions!$F$24),((Assumptions!$F$9/2*Assumptions!$F$13)*Assumptions!$F$16*Assumptions!$F$24*Assumptions!$F$98)))*V22+((V16*Assumptions!$F$25))*V23 -> 18405935
B28: Cake/powder revenue ($) | C28: =(MAX((C17*Assumptions!$F$24),((Assumptions!$F$9/2*Assumptions!$F$13)*Assumptions!$F$17*Assumptions!$F$24*Assumptions!$F$98)))*C24+((C17*Assumptions!$F$25))*C25 -> 10385070 | D28: =(MAX((D17*Assumptions!$F$24),((Assumptions!$F$9/2*Assumptions!$F$13)*Assumptions!$F$17*Assumptions!$F$24*Assumptions!$F$98)))*D24+((D17*Assumptions!$F$25))*D25 -> 11462573 | E28: =(MAX((E17*Assumptions!$F$24),((Assumptions!$F$9/2*Assumptions!$F$13)*Assumptions!$F$17*Assumptions!$F$24*Assumptions!$F$98)))*E24+((E17*Assumptions!$F$25))*E25 -> 11646864 | F28: =(MAX((F17*Assumptions!$F$24),((Assumptions!$F$9/2*Assumptions!$F$13)*Assumptions!$F$17*Assumptions!$F$24*Assumptions!$F$98)))*F24+((F17*Assumptions!$F$25))*F25 -> 11779304 | G28: =(MAX((G17*Assumptions!$F$24),((Assumptions!$F$9/2*Assumptions!$F$13)*Assumptions!$F$17*Assumptions!$F$24*Assumptions!$F$98)))*G24+((G17*Assumptions!$F$25))*G25 -> 12865788 | H28: =(MAX((H17*Assumptions!$F$24),((Assumptions!$F$9/2*Assumptions!$F$13)*Assumptions!$F$17*Assumptions!$F$24*Assumptions!$F$98)))*H24+((H17*Assumptions!$F$25))*H25 -> 13011909 | I28: =(MAX((I17*Assumptions!$F$24),((Assumptions!$F$9/2*Assumptions!$F$13)*Assumptions!$F$17*Assumptions!$F$24*Assumptions!$F$98)))*I24+((I17*Assumptions!$F$25))*I25 -> 13159628 | J28: =(MAX((J17*Assumptions!$F$24),((Assumptions!$F$9/2*Assumptions!$F$13)*Assumptions!$F$17*Assumptions!$F$24*Assumptions!$F$98)))*J24+((J17*Assumptions!$F$25))*J25 -> 13308963 | ... V28: =(MAX((V17*Assumptions!$F$24),((Assumptions!$F$9/2*Assumptions!$F$13)*Assumptions!$F$17*Assumptions!$F$24*Assumptions!$F$98)))*V24+((V17*Assumptions!$F$25))*V25 -> 15277276
B29: Total Product Revenue ($) | C29: =SUM(C26:C28) -> 39037452 | D29: =SUM(D26:D28) -> 42837975 | E29: =SUM(E26:E28) -> 43463879 | F29: =SUM(F26:F28) -> 43905345 | G29: =SUM(G26:G28) -> 47846029 | H29: =SUM(H26:H28) -> 48333097 | I29: =SUM(I26:I28) -> 48825494 | J29: =SUM(J26:J28) -> 49323278 | ... V29: =SUM(V26:V28) -> 55443428
B30: Bean Procurement (GHS, Converted to USD)
B31: Bean requirement (MT) | C31: =C14*Assumptions!$F$14 -> 3150 | D31: =D14*Assumptions!$F$14 -> 5850 | E31: =E14*Assumptions!$F$14 -> 6000 | F31: =F14*Assumptions!$F$14 -> 6000 | G31: =G14*Assumptions!$F$14 -> 7125 | H31: =H14*Assumptions!$F$14 -> 7125 | I31: =I14*Assumptions!$F$14 -> 7125 | J31: =J14*Assumptions!$F$14 -> 7125 | ... V31: =V14*Assumptions!$F$14 -> 7125
B32: COCOBOD producer price (t) (GHS/64kg bag) | C32: =Assumptions!$F$29*(1+Assumptions!$F$30)^C10*(1+Assumptions!$F$105*((C19/(Assumptions!$F$20*(1+Assumptions!$F$49)^C10))-1)) -> 3086.212 | D32: =Assumptions!$F$29*(1+Assumptions!$F$30)^D10*(1+Assumptions!$F$105*((D19/(Assumptions!$F$20*(1+Assumptions!$F$49)^D10))-1)) -> 3266.1398 | E32: =Assumptions!$F$29*(1+Assumptions!$F$30)^E10*(1+Assumptions!$F$105*((E19/(Assumptions!$F$20*(1+Assumptions!$F$49)^E10))-1)) -> 3456.5575 | F32: =Assumptions!$F$29*(1+Assumptions!$F$30)^F10*(1+Assumptions!$F$105*((F19/(Assumptions!$F$20*(1+Assumptions!$F$49)^F10))-1)) -> 3658.0766 | G32: =Assumptions!$F$29*(1+Assumptions!$F$30)^G10*(1+Assumptions!$F$105*((G19/(Assumptions!$F$20*(1+Assumptions!$F$49)^G10))-1)) -> 3871.3444 | H32: =Assumptions!$F$29*(1+Assumptions!$F$30)^H10*(1+Assumptions!$F$105*((H19/(Assumptions!$F$20*(1+Assumptions!$F$49)^H10))-1)) -> 4097.0458 | I32: =Assumptions!$F$29*(1+Assumptions!$F$30)^I10*(1+Assumptions!$F$105*((I19/(Assumptions!$F$20*(1+Assumptions!$F$49)^I10))-1)) -> 4335.9057 | J32: =Assumptions!$F$29*(1+Assumptions!$F$30)^J10*(1+Assumptions!$F$105*((J19/(Assumptions!$F$20*(1+Assumptions!$F$49)^J10))-1)) -> 4588.6913 | ... V32: =Assumptions!$F$29*(1+Assumptions!$F$30)^V10*(1+Assumptions!$F$105*((V19/(Assumptions!$F$20*(1+Assumptions!$F$49)^V10))-1)) -> 9057.2629
B33: GHS cost per MT beans | C33: =C32/Assumptions!$F$31*1000 -> 48222.063 | D33: =D32/Assumptions!$F$31*1000 -> 51033.435 | E33: =E32/Assumptions!$F$31*1000 -> 54008.711 | F33: =F32/Assumptions!$F$31*1000 -> 57157.447 | G33: =G32/Assumptions!$F$31*1000 -> 60489.756 | H33: =H32/Assumptions!$F$31*1000 -> 64016.34 | I33: =I32/Assumptions!$F$31*1000 -> 67748.527 | J33: =J32/Assumptions!$F$31*1000 -> 71698.301 | ... V33: =V32/Assumptions!$F$31*1000 -> 141519.73
B34: FX rate (t) (GHS per USD) | C34: =Assumptions!$F$32*(1+Assumptions!$F$33)^C10 -> 13.159539 | D34: =Assumptions!$F$32*(1+Assumptions!$F$33)^D10 -> 13.484515 | E34: =Assumptions!$F$32*(1+Assumptions!$F$33)^E10 -> 13.817516 | F34: =Assumptions!$F$32*(1+Assumptions!$F$33)^F10 -> 14.158741 | G34: =Assumptions!$F$32*(1+Assumptions!$F$33)^G10 -> 14.508392 | H34: =Assumptions!$F$32*(1+Assumptions!$F$33)^H10 -> 14.866678 | I34: =Assumptions!$F$32*(1+Assumptions!$F$33)^I10 -> 15.233811 | J34: =Assumptions!$F$32*(1+Assumptions!$F$33)^J10 -> 15.610012 | ... V34: =Assumptions!$F$32*(1+Assumptions!$F$33)^V10 -> 20.918908
B35: Bean cost (GHS) | C35: =C31*C33 -> 1.518995e+08 | D35: =D31*D33 -> 2.9854559e+08 | E35: =E31*E33 -> 3.2405226e+08 | F35: =F31*F33 -> 3.4294468e+08 | G35: =G31*G33 -> 4.3098951e+08 | H35: =H31*H33 -> 4.5611643e+08 | I35: =I31*I33 -> 4.8270825e+08 | J35: =J31*J33 -> 5.108504e+08 | ... V35: =V31*V33 -> 1.0083281e+09
B36: Bean cost (USD) | C36: =C35*((IF(C8<=2,Assumptions!$F$78,0))/Assumptions!$F$32+(1-(IF(C8<=2,Assumptions!$F$78,0)))/C34) -> 11613748 | D36: =D35*((IF(D8<=2,Assumptions!$F$78,0))/Assumptions!$F$32+(1-(IF(D8<=2,Assumptions!$F$78,0)))/D34) -> 22552465 | E36: =E35*((IF(E8<=2,Assumptions!$F$78,0))/Assumptions!$F$32+(1-(IF(E8<=2,Assumptions!$F$78,0)))/E34) -> 24189689 | F36: =F35*((IF(F8<=2,Assumptions!$F$78,0))/Assumptions!$F$32+(1-(IF(F8<=2,Assumptions!$F$78,0)))/F34) -> 25300886 | G36: =G35*((IF(G8<=2,Assumptions!$F$78,0))/Assumptions!$F$32+(1-(IF(G8<=2,Assumptions!$F$78,0)))/G34) -> 29706222 | H36: =H35*((IF(H8<=2,Assumptions!$F$78,0))/Assumptions!$F$32+(1-(IF(H8<=2,Assumptions!$F$78,0)))/H34) -> 30680454 | I36: =I35*((IF(I8<=2,Assumptions!$F$78,0))/Assumptions!$F$32+(1-(IF(I8<=2,Assumptions!$F$78,0)))/I34) -> 31686637 | J36: =J35*((IF(J8<=2,Assumptions!$F$78,0))/Assumptions!$F$32+(1-(IF(J8<=2,Assumptions!$F$78,0)))/J34) -> 32725818 | ... V36: =V35*((IF(V8<=2,Assumptions!$F$78,0))/Assumptions!$F$32+(1-(IF(V8<=2,Assumptions!$F$78,0)))/V34) -> 48201755
B37: Other Operating Costs (USD)
B38: O&M rate (t) ($/MT processed) | C38: =Assumptions!$F$37*(1+Assumptions!$F$49)^C10 -> 955.18244 | D38: =Assumptions!$F$37*(1+Assumptions!$F$49)^D10 -> 965.63228 | E38: =Assumptions!$F$37*(1+Assumptions!$F$49)^E10 -> 976.19645 | F38: =Assumptions!$F$37*(1+Assumptions!$F$49)^F10 -> 986.87619 | G38: =Assumptions!$F$37*(1+Assumptions!$F$49)^G10 -> 997.67277 | H38: =Assumptions!$F$37*(1+Assumptions!$F$49)^H10 -> 1008.5875 | I38: =Assumptions!$F$37*(1+Assumptions!$F$49)^I10 -> 1019.6216 | J38: =Assumptions!$F$37*(1+Assumptions!$F$49)^J10 -> 1030.7764 | ... V38: =Assumptions!$F$37*(1+Assumptions!$F$49)^V10 -> 1174.5455
B39: O&M cost (USD) | C39: =C13*C38 -> 3008824.7 | D39: =D13*D38 -> 5648948.9 | E39: =E13*E38 -> 5857178.7 | F39: =F13*F38 -> 5921257.2 | G39: =G13*G38 -> 7108418.5 | H39: =H13*H38 -> 7186185.7 | I39: =I13*I38 -> 7264803.7 | J39: =J13*J38 -> 7344281.8 | ... V39: =V13*V38 -> 8368636.6
B40: Logistics rate (t) ($/MT product) | C40: =Assumptions!$F$38*(1+Assumptions!$F$49)^C10 -> 45.245484 | D40: =Assumptions!$F$38*(1+Assumptions!$F$49)^D10 -> 45.740477 | E40: =Assumptions!$F$38*(1+Assumptions!$F$49)^E10 -> 46.240885 | F40: =Assumptions!$F$38*(1+Assumptions!$F$49)^F10 -> 46.746767 | G40: =Assumptions!$F$38*(1+Assumptions!$F$49)^G10 -> 47.258184 | H40: =Assumptions!$F$38*(1+Assumptions!$F$49)^H10 -> 47.775196 | I40: =Assumptions!$F$38*(1+Assumptions!$F$49)^I10 -> 48.297864 | J40: =Assumptions!$F$38*(1+Assumptions!$F$49)^J10 -> 48.82625 | ... V40: =Assumptions!$F$38*(1+Assumptions!$F$49)^V10 -> 55.636365
B41: Logistics/freight cost (USD) | C41: =C14*C40 -> 121144.78 | D41: =D14*D40 -> 227444.52 | E41: =E14*E40 -> 235828.51 | F41: =F14*F40 -> 238408.51 | G41: =G14*G40 -> 286207.38 | H41: =H14*H40 -> 289338.53 | I41: =I14*I40 -> 292503.94 | J41: =J14*J40 -> 295703.98 | ... V41: =V14*V40 -> 336947.74
B42: Total Cash Opex (USD) | C42: =C36+C39+C41 -> 14743718 | D42: =D36+D39+D41 -> 28428858 | E42: =E36+E39+E41 -> 30282696 | F42: =F36+F39+F41 -> 31460551 | G42: =G36+G39+G41 -> 37100848 | H42: =H36+H39+H41 -> 38155979 | I42: =I36+I39+I41 -> 39243945 | J42: =J36+J39+J41 -> 40365804 | ... V42: =V36+V39+V41 -> 56907339
B43: EBITDA, Tax & CFADS
B44: EBITDA (USD) | C44: =C29-C42 -> 24293734 | D44: =D29-D42 -> 14409116 | E44: =E29-E42 -> 13181182 | F44: =F29-F42 -> 12444794 | G44: =G29-G42 -> 10745181 | H44: =H29-H42 -> 10177119 | I44: =I29-I42 -> 9581549.4 | J44: =J29-J42 -> 8957474.1 | ... V44: =V29-V42 -> -1463911
B45: Tax depreciation (USD) | C45: =(Construction!$D$6+Construction!$I$29+Construction!$M$29+Construction!$D$45)/Assumptions!$F$53/2 -> 10367157 | D45: =(Construction!$D$6+Construction!$I$29+Construction!$M$29+Construction!$D$45)/Assumptions!$F$53/2 -> 10367157 | E45: =(Construction!$D$6+Construction!$I$29+Construction!$M$29+Construction!$D$45)/Assumptions!$F$53/2 -> 10367157 | F45: =(Construction!$D$6+Construction!$I$29+Construction!$M$29+Construction!$D$45)/Assumptions!$F$53/2 -> 10367157 | G45: =(Construction!$D$6+Construction!$I$29+Construction!$M$29+Construction!$D$45)/Assumptions!$F$53/2 -> 10367157 | H45: =(Construction!$D$6+Construction!$I$29+Construction!$M$29+Construction!$D$45)/Assumptions!$F$53/2 -> 10367157 | I45: =(Construction!$D$6+Construction!$I$29+Construction!$M$29+Construction!$D$45)/Assumptions!$F$53/2 -> 10367157 | J45: =(Construction!$D$6+Construction!$I$29+Construction!$M$29+Construction!$D$45)/Assumptions!$F$53/2 -> 10367157 | ... V45: =(Construction!$D$6+Construction!$I$29+Construction!$M$29+Construction!$D$45)/Assumptions!$F$53/2 -> 10367157
B46: Senior Interest Expense ($) [from Debt sheet] | C46: =Debt!C9 -> 6010214.1 | D46: =Debt!D9 -> 5408043.6 | E46: =Debt!E9 -> 5138438.7 | F46: =Debt!F9 -> 4900894.4 | G46: =Debt!G9 -> 4678973.3 | H46: =Debt!H9 -> 4508612.1 | I46: =Debt!I9 -> 4350915 | J46: =Debt!J9 -> 4207488.4 | ... V46: =Debt!V9 -> 3811030
B47: Taxable Income ($, = EBITDA - Depreciation - Senior Interest - Mezz Interest) | C47: =C44-C45-C46-Debt!C36 -> 5661500.3 | D47: =D44-D45-D46-Debt!D36 -> -3603313.6 | E47: =E44-E45-E46-Debt!E36 -> -4060422.7 | F47: =F44-F45-F46-Debt!F36 -> -4516285.1 | G47: =G44-G45-G46-Debt!G36 -> -5994351.3 | H47: =H44-H45-H46-Debt!H36 -> -6504624.7 | I47: =I44-I45-I46-Debt!I36 -> -7011103.5 | J47: =J44-J45-J46-Debt!J36 -> -7605337.8 | ... V47: =V44-V45-V46-Debt!V36 -> -19984125
B48: Effective tax rate applied | C48: =IF(Assumptions!$F$51="Yes",IF(C8<=Assumptions!$F$52,0,Assumptions!$F$50),Assumptions!$F$50) -> 0 | D48: =IF(Assumptions!$F$51="Yes",IF(D8<=Assumptions!$F$52,0,Assumptions!$F$50),Assumptions!$F$50) -> 0 | E48: =IF(Assumptions!$F$51="Yes",IF(E8<=Assumptions!$F$52,0,Assumptions!$F$50),Assumptions!$F$50) -> 0 | F48: =IF(Assumptions!$F$51="Yes",IF(F8<=Assumptions!$F$52,0,Assumptions!$F$50),Assumptions!$F$50) -> 0 | G48: =IF(Assumptions!$F$51="Yes",IF(G8<=Assumptions!$F$52,0,Assumptions!$F$50),Assumptions!$F$50) -> 0 | H48: =IF(Assumptions!$F$51="Yes",IF(H8<=Assumptions!$F$52,0,Assumptions!$F$50),Assumptions!$F$50) -> 0 | I48: =IF(Assumptions!$F$51="Yes",IF(I8<=Assumptions!$F$52,0,Assumptions!$F$50),Assumptions!$F$50) -> 0 | J48: =IF(Assumptions!$F$51="Yes",IF(J8<=Assumptions!$F$52,0,Assumptions!$F$50),Assumptions!$F$50) -> 0 | ... V48: =IF(Assumptions!$F$51="Yes",IF(V8<=Assumptions!$F$52,0,Assumptions!$F$50),Assumptions!$F$50) -> 0
B49: Cash tax (USD) | C49: =MAX(0,C47)*C48 -> 0 | D49: =MAX(0,D47)*D48 -> 0 | E49: =MAX(0,E47)*E48 -> 0 | F49: =MAX(0,F47)*F48 -> 0 | G49: =MAX(0,G47)*G48 -> 0 | H49: =MAX(0,H47)*H48 -> 0 | I49: =MAX(0,I47)*I48 -> 0 | J49: =MAX(0,J47)*J48 -> 0 | ... V49: =MAX(0,V47)*V48 -> 0
B50: CFADS (USD) | C50: =C44-C49 -> 24293734 | D50: =D44-D49 -> 14409116 | E50: =E44-E49 -> 13181182 | F50: =F44-F49 -> 12444794 | G50: =G44-G49 -> 10745181 | H50: =H44-H49 -> 10177119 | I50: =I44-I49 -> 9581549.4 | J50: =J44-J49 -> 8957474.1 | ... V50: =V44-V49 -> -1463911

Sheet Debt
B2: Debt & Financing — Sculpted Senior Term Loan
B4: Repayment each period is sized so scheduled debt service never exceeds CFADS / Target DSCR; final period forces full repayment (bullet true-up).
B5: Active Scenario: | C5: =Cover!$C$9 -> Base | D5: <<<< Cover
B6: Senior Debt Amortisation Schedule (Semi-Annual)
B7: Period # | C7: 1 | D7: 2 | E7: 3 | F7: 4 | G7: 5 | H7: 6 | I7: 7 | J7: 8 | K7: 9 | L7: 10 | M7: 11 | N7: 12 | O7: 13 | P7: 14 | Q7: 15 | R7: 16 | S7: 17 | T7: 18 | U7: 19 | V7: 20
B8: Opening Debt Balance ($) | C8: =Construction!$D$46 -> 1.2653082e+08 | D8: =C14 -> 1.1385355e+08 | E8: =D14 -> 1.0817766e+08 | F8: =E14 -> 1.0317672e+08 | G8: =F14 -> 98504701 | H8: =G14 -> 94918151 | I8: =H14 -> 91598210 | J8: =I14 -> 88578702 | K8: =J14 -> 85895826 | ... V8: =U14 -> 80232210
B9: Interest Expense ($) | C9: =C8*Assumptions!$F$42/2 -> 6010214.1 | D9: =D8*Assumptions!$F$42/2 -> 5408043.6 | E9: =E8*Assumptions!$F$42/2 -> 5138438.7 | F9: =F8*Assumptions!$F$42/2 -> 4900894.4 | G9: =G8*Assumptions!$F$42/2 -> 4678973.3 | H9: =H8*Assumptions!$F$42/2 -> 4508612.1 | I9: =I8*Assumptions!$F$42/2 -> 4350915 | J9: =J8*Assumptions!$F$42/2 -> 4207488.4 | ... V9: =V8*Assumptions!$F$42/2 -> 3811030
B10: CFADS ($) [from Operations] | C10: =Operations!C50 -> 24293734 | D10: =Operations!D50 -> 14409116 | E10: =Operations!E50 -> 13181182 | F10: =Operations!F50 -> 12444794 | G10: =Operations!G50 -> 10745181 | H10: =Operations!H50 -> 10177119 | I10: =Operations!I50 -> 9581549.4 | J10: =Operations!J50 -> 8957474.1 | ... V10: =Operations!V50 -> -1463911
B11: Target Debt Service = CFADS / Target DSCR ($) | C11: =C10/Assumptions!$F$45 -> 18687488 | D11: =D10/Assumptions!$F$45 -> 11083936 | E11: =E10/Assumptions!$F$45 -> 10139371 | F11: =F10/Assumptions!$F$45 -> 9572918.5 | G11: =G10/Assumptions!$F$45 -> 8265523.6 | H11: =H10/Assumptions!$F$45 -> 7828552.7 | I11: =I10/Assumptions!$F$45 -> 7370422.6 | J11: =J10/Assumptions!$F$45 -> 6890364.7 | ... V11: =V10/Assumptions!$F$45 -> -1126085.4
B12: Principal Repayment ($) | C12: =MAX(0,MIN(C8,C11-C9)) -> 12677274 | D12: =MAX(0,MIN(D8,D11-D9)) -> 5675892.1 | E12: =MAX(0,MIN(E8,E11-E9)) -> 5000932.4 | F12: =MAX(0,MIN(F8,F11-F9)) -> 4672024.1 | G12: =MAX(0,MIN(G8,G11-G9)) -> 3586550.3 | H12: =MAX(0,MIN(H8,H11-H9)) -> 3319940.5 | I12: =MAX(0,MIN(I8,I11-I9)) -> 3019507.6 | J12: =MAX(0,MIN(J8,J11-J9)) -> 2682876.3 | ... U12: =MAX(0,MIN(U8,U11-U9)) -> 0 | V12: =V8 -> 80232210
B13: Total Debt Service ($) | C13: =C9+C12 -> 18687488 | D13: =D9+D12 -> 11083936 | E13: =E9+E12 -> 10139371 | F13: =F9+F12 -> 9572918.5 | G13: =G9+G12 -> 8265523.6 | H13: =H9+H12 -> 7828552.7 | I13: =I9+I12 -> 7370422.6 | J13: =J9+J12 -> 6890364.7 | ... V13: =V9+V12 -> 84043240
B14: Closing Debt Balance ($) | C14: =C8-C12 -> 1.1385355e+08 | D14: =D8-D12 -> 1.0817766e+08 | E14: =E8-E12 -> 1.0317672e+08 | F14: =F8-F12 -> 98504701 | G14: =G8-G12 -> 94918151 | H14: =H8-H12 -> 91598210 | I14: =I8-I12 -> 88578702 | J14: =J8-J12 -> 85895826 | ... V14: =V8-V12 -> 0
B15: DSCR (x) | C15: =IFERROR(C10/C13,"n/a") -> 1.3 | D15: =IFERROR(D10/D13,"n/a") -> 1.3 | E15: =IFERROR(E10/E13,"n/a") -> 1.3 | F15: =IFERROR(F10/F13,"n/a") -> 1.3 | G15: =IFERROR(G10/G13,"n/a") -> 1.3 | H15: =IFERROR(H10/H13,"n/a") -> 1.3 | I15: =IFERROR(I10/I13,"n/a") -> 1.3 | J15: =IFERROR(J10/J13,"n/a") -> 1.3 | ... V15: =IFERROR(V10/V13,"n/a") -> -0.017418545
B16: Cumulative Principal Repaid ($) | C16: =C12 -> 12677274 | D16: =C16+D12 -> 18353166 | E16: =D16+E12 -> 23354098 | F16: =E16+F12 -> 28026122 | G16: =F16+G12 -> 31612673 | H16: =G16+H12 -> 34932613 | I16: =H16+I12 -> 37952121 | J16: =I16+J12 -> 40634997 | K16: =J16+K12 -> 42715188 | ... V16: =U16+V12 -> 1.2653082e+08
B18: Credit Metrics & Checks
B19: Minimum DSCR, Periods 1-19 (excl. final bullet) | D19: =MIN(C15:U15) -> -0.10661364
B20: Minimum DSCR, All 20 periods | D20: =MIN(C15:V15) -> -0.10661364
B21: Average DSCR, All periods | D21: =AVERAGE(C15:V15) -> 1.0009806
B22: Debt fully repaid by maturity (Closing Bal. Period 20) | D22: =V14 -> 0
B23: Target minimum DSCR (active scenario) | D23: =Assumptions!$F$45 -> 1.3
B24: Check: Min DSCR (periods 1-19) >= Target | D24: =IF(D19>=D23-0.001,"OK","FAIL") -> FAIL
B26: Loan Life Coverage Ratio (LLCR) & Project Life Coverage Ratio (PLCR) at COD
B27: PV of CFADS, Period 1-20 (discounted @ senior interest rate) | D27: =NPV(Assumptions!$F$42/2,C10:V10) -> 1.1278617e+08
B28: Senior Debt Balance at COD ($) | D28: =Construction!$D$46 -> 1.2653082e+08
B29: LLCR at COD (x) [= PV of CFADS over loan life / Debt at COD] | D29: =D27/D28 -> 0.89137311
B30: PLCR at COD (x) [project life = debt tenor in this model, so PLCR = LLCR] | D30: =D29 -> 0.89137311
B33: Mezzanine Debt Amortisation Schedule (Subordinated, Cash-Sweep)
B34: Period # | C34: 1 | D34: 2 | E34: 3 | F34: 4 | G34: 5 | H34: 6 | I34: 7 | J34: 8 | K34: 9 | L34: 10 | M34: 11 | N34: 12 | O34: 13 | P34: 14 | Q34: 15 | R34: 16 | S34: 17 | T34: 18 | U34: 19 | V34: 20
B35: Opening Mezzanine Balance ($) | C35: =Construction!$D$56 -> 32212323 | D35: =C40 -> 31960416 | E35: =D40 -> 24800130 | F35: =E40 -> 24186107 | G35: =F40 -> 24191449 | H35: =G40 -> 25799625 | I35: =H40 -> 26779723 | J35: =I40 -> 28402375 | K35: =J40 -> 29827998 | ... V35: =U40 -> 62028947
B36: Mezzanine Interest Expense ($) | C36: =C35*Assumptions!$F$76/2 -> 2254862.6 | D36: =D35*Assumptions!$F$76/2 -> 2237229.1 | E36: =E35*Assumptions!$F$76/2 -> 1736009.1 | F36: =F35*Assumptions!$F$76/2 -> 1693027.5 | G36: =G35*Assumptions!$F$76/2 -> 1693401.4 | H36: =H35*Assumptions!$F$76/2 -> 1805973.8 | I36: =I35*Assumptions!$F$76/2 -> 1874580.6 | J36: =J35*Assumptions!$F$76/2 -> 1988166.3 | ... V36: =V35*Assumptions!$F$76/2 -> 4342026.3
B37: Cash Available for Mezz Service (post Senior DS, DSRA, MRA, VAT, NWC & Revolver) ($) | C37: =Waterfall!C30 -> 2506768.8 | D37: =Waterfall!D30 -> 9397515.1 | E37: =Waterfall!E30 -> 2350032.7 | F37: =Waterfall!F30 -> 1687685.1 | G37: =Waterfall!G30 -> 85225.519 | H37: =Waterfall!H30 -> 825875.83 | I37: =Waterfall!I30 -> 251928.41 | J37: =Waterfall!J30 -> 562543.87 | ... V37: =Waterfall!V30 -> -83842484
B38: Mezzanine Principal Repayment ($) | C38: =MAX(0,MIN(C35,C37-C51)) -> 251906.21 | D38: =MAX(0,MIN(D35,D37-D51)) -> 7160286 | E38: =MAX(0,MIN(E35,E37-E51)) -> 614023.57 | F38: =MAX(0,MIN(F35,F37-F51)) -> 0 | G38: =MAX(0,MIN(G35,G37-G51)) -> 0 | H38: =MAX(0,MIN(H35,H37-H51)) -> 0 | I38: =MAX(0,MIN(I35,I37-I51)) -> 0 | J38: =MAX(0,MIN(J35,J37-J51)) -> 0 | ... U38: =MAX(0,MIN(U35,U37-U51)) -> 0 | V38: =V35 -> 62028947
B39: Mezzanine Total Debt Service, Cash Basis ($, = cash interest + principal) | C39: =C51+C38 -> 2506768.8 | D39: =D51+D38 -> 9397515.1 | E39: =E51+E38 -> 2350032.7 | F39: =F51+F38 -> 1687685.1 | G39: =G51+G38 -> 85225.519 | H39: =H51+H38 -> 825875.83 | I39: =I51+I38 -> 251928.41 | J39: =J51+J38 -> 562543.87 | ... V39: =V51+V38 -> 66370973
B40: Mezzanine Closing Balance ($) | C40: =C35+C52-C38 -> 31960416 | D40: =D35+D52-D38 -> 24800130 | E40: =E35+E52-E38 -> 24186107 | F40: =F35+F52-F38 -> 24191449 | G40: =G35+G52-G38 -> 25799625 | H40: =H35+H52-H38 -> 26779723 | I40: =I35+I52-I38 -> 28402375 | J40: =J35+J52-J38 -> 29827998 | ... V40: =V35+V52-V38 -> 0
B42: Leverage Covenant & Rolling Loan Life Coverage
B43: Annualised EBITDA ($, = period EBITDA x 2) | C43: =Operations!C44*2 -> 48587469 | D43: =Operations!D44*2 -> 28818233 | E43: =Operations!E44*2 -> 26362365 | F43: =Operations!F44*2 -> 24889588 | G43: =Operations!G44*2 -> 21490361 | H43: =Operations!H44*2 -> 20354237 | I43: =Operations!I44*2 -> 19163099 | J43: =Operations!J44*2 -> 17914948 | ... V43: =Operations!V44*2 -> -2927822
B44: Senior Leverage (Opening Senior Debt / Annualised EBITDA) (x) | C44: =C8/C43 -> 2.6041864 | D44: =D8/D43 -> 3.9507471 | E44: =E8/E43 -> 4.1034884 | F44: =F8/F43 -> 4.145377 | G44: =G8/G43 -> 4.5836689 | H44: =H8/H43 -> 4.6633116 | I44: =I8/I43 -> 4.7799268 | J44: =J8/J43 -> 4.9444018 | ... V44: =V8/V43 -> -27.403377
B45: Total Leverage incl. Mezz (x) | C45: =(C8+C35)/C43 -> 3.2671623 | D45: =(D8+D35)/D43 -> 5.0597816 | E45: =(E8+E35)/E43 -> 5.0442283 | F45: =(F8+F35)/F43 -> 5.1171129 | G45: =(G8+G35)/G43 -> 5.7093572 | H45: =(H8+H35)/H43 -> 5.9308426 | I45: =(I8+I35)/I43 -> 6.1773899 | J45: =(J8+J35)/J43 -> 6.5298027 | ... V45: =(V8+V35)/V43 -> -48.589415
B46: Maximum leverage covenant (x) | C46: =Assumptions!$F$82 -> 5 | D46: =Assumptions!$F$82 -> 5 | E46: =Assumptions!$F$82 -> 5 | F46: =Assumptions!$F$82 -> 5 | G46: =Assumptions!$F$82 -> 5 | H46: =Assumptions!$F$82 -> 5 | I46: =Assumptions!$F$82 -> 5 | J46: =Assumptions!$F$82 -> 5 | ... V46: =Assumptions!$F$82 -> 5
B47: Check: Leverage <= covenant maximum | C47: =IF(C44<=C46,"OK","REVIEW") -> OK | D47: =IF(D44<=D46,"OK","REVIEW") -> OK | E47: =IF(E44<=E46,"OK","REVIEW") -> OK | F47: =IF(F44<=F46,"OK","REVIEW") -> OK | G47: =IF(G44<=G46,"OK","REVIEW") -> OK | H47: =IF(H44<=H46,"OK","REVIEW") -> OK | I47: =IF(I44<=I46,"OK","REVIEW") -> OK | J47: =IF(J44<=J46,"OK","REVIEW") -> OK | ... V47: =IF(V44<=V46,"OK","REVIEW") -> OK
B48: Rolling LLCR (PV of forward CFADS to maturity / opening senior debt) (x) | C48: =IFERROR(NPV(Assumptions!$F$42/2,C10:V10)/C8,"n/a") -> 0.89137311 | D48: =IFERROR(NPV(Assumptions!$F$42/2,D10:V10)/D8,"n/a") -> 0.82430265 | E48: =IFERROR(NPV(Assumptions!$F$42/2,E10:V10)/E8,"n/a") -> 0.77556247 | F48: =IFERROR(NPV(Assumptions!$F$42/2,F10:V10)/F8,"n/a") -> 0.724025 | G48: =IFERROR(NPV(Assumptions!$F$42/2,G10:V10)/G8,"n/a") -> 0.6680504 | H48: =IFERROR(NPV(Assumptions!$F$42/2,H10:V10)/H8,"n/a") -> 0.61301989 | I48: =IFERROR(NPV(Assumptions!$F$42/2,I10:V10)/I8,"n/a") -> 0.55430629 | J48: =IFERROR(NPV(Assumptions!$F$42/2,J10:V10)/J8,"n/a") -> 0.4922589 | K48: =IFERROR(NPV(Assumptions!$F$42/2,K10:V10)/K8,"n/a") -> 0.42746378 | L48: =IFERROR(NPV(Assumptions!$F$42/2,L10:V10)/L8,"n/a") -> 0.36333452 | M48: =IFERROR(NPV(Assumptions!$F$42/2,M10:V10)/M8,"n/a") -> 0.29910733 | N48: =IFERROR(NPV(Assumptions!$F$42/2,N10:V10)/N8,"n/a") -> 0.23628218 | O48: =IFERROR(NPV(Assumptions!$F$42/2,O10:V10)/O8,"n/a") -> 0.1765924 | P48: =IFERROR(NPV(Assumptions!$F$42/2,P10:V10)/P8,"n/a") -> 0.12191417 | Q48: =IFERROR(NPV(Assumptions!$F$42/2,Q10:V10)/Q8,"n/a") -> 0.074628098 | R48: =IFERROR(NPV(Assumptions!$F$42/2,R10:V10)/R8,"n/a") -> 0.035747325 | S48: =IFERROR(NPV(Assumptions!$F$42/2,S10:V10)/S8,"n/a") -> 0.0061424466 | T48: =IFERROR(NPV(Assumptions!$F$42/2,T10:V10)/T8,"n/a") -> -0.013257797 | U48: =IFERROR(NPV(Assumptions!$F$42/2,U10:V10)/U8,"n/a") -> -0.021463191 | V48: =IFERROR(NPV(Assumptions!$F$42/2,V10:V10)/V8,"n/a") -> -0.017418545
B50: Mezzanine Cash-Pay / PIK Mechanic (cures the cash-pay interest shortfall found in audit)
B51: Mezzanine Interest Paid in Cash ($, capped at cash available) | C51: =MIN(C36,MAX(0,C37)) -> 2254862.6 | D51: =MIN(D36,MAX(0,D37)) -> 2237229.1 | E51: =MIN(E36,MAX(0,E37)) -> 1736009.1 | F51: =MIN(F36,MAX(0,F37)) -> 1687685.1 | G51: =MIN(G36,MAX(0,G37)) -> 85225.519 | H51: =MIN(H36,MAX(0,H37)) -> 825875.83 | I51: =MIN(I36,MAX(0,I37)) -> 251928.41 | J51: =MIN(J36,MAX(0,J37)) -> 562543.87 | ... U51: =MIN(U36,MAX(0,U37)) -> 0 | V51: =V36 -> 4342026.3
B52: Mezzanine Interest Capitalised — PIK shortfall ($) | C52: =C36-C51 -> 0 | D52: =D36-D51 -> 0 | E52: =E36-E51 -> 0 | F52: =F36-F51 -> 5342.3992 | G52: =G36-G51 -> 1608175.9 | H52: =H36-H51 -> 980097.93 | I52: =I36-I51 -> 1622652.2 | J52: =J36-J51 -> 1425622.4 | ... U52: =U36-U51 -> 4057968.5 | V52: 0

Sheet Waterfall
B2: Cash Flow Waterfall
B4: Priority of payments: Opex/Cash Tax (in Operations) -> Senior Debt Service -> Mezzanine Debt Service -> DSRA & MRA top-up/(release) -> VAT bridge one-off cost -> Net working-capital funding & revolver interest -> Distribution lock-up test -> Equity Distributions (gross of dividend withholding tax, applied on Outputs).
B5: Active Scenario: | C5: =Cover!$C$9 -> Base | D5: <<<< Cover
B6: Waterfall (Semi-Annual)
B7: CFADS ($) [from Operations] | C7: =Operations!C50 -> 24293734 | D7: =Operations!D50 -> 14409116 | E7: =Operations!E50 -> 13181182 | F7: =Operations!F50 -> 12444794 | G7: =Operations!G50 -> 10745181 | H7: =Operations!H50 -> 10177119 | I7: =Operations!I50 -> 9581549.4 | J7: =Operations!J50 -> 8957474.1 | ... V7: =Operations!V50 -> -1463911
B8: Less: Total Senior Debt Service ($) [from Debt] | C8: =Debt!C13 -> 18687488 | D8: =Debt!D13 -> 11083936 | E8: =Debt!E13 -> 10139371 | F8: =Debt!F13 -> 9572918.5 | G8: =Debt!G13 -> 8265523.6 | H8: =Debt!H13 -> 7828552.7 | I8: =Debt!I13 -> 7370422.6 | J8: =Debt!J13 -> 6890364.7 | ... V8: =Debt!V13 -> 84043240
B9: Cash Flow after Debt Service ($) | C9: =C7-C8 -> 5606246.4 | D9: =D7-D8 -> 3325180.7 | E9: =E7-E8 -> 3041811.3 | F9: =F7-F8 -> 2871875.6 | G9: =G7-G8 -> 2479657.1 | H9: =H7-H8 -> 2348565.8 | I9: =I7-I8 -> 2211126.8 | J9: =J7-J8 -> 2067109.4 | ... V9: =V7-V8 -> -85507151
B10: Less/(Plus): DSRA Movement — top-up/(release) ($) [from Reserves] | C10: =Reserves!C11 -> 0 | D10: =Reserves!D11 -> -7603552.2 | E10: =Reserves!E11 -> -944564.63 | F10: =Reserves!F11 -> -566452.61 | G10: =Reserves!G11 -> -1307394.9 | H10: =Reserves!H11 -> -436970.93 | I10: =Reserves!I11 -> -458130.1 | J10: =Reserves!J11 -> -480057.91 | ... V10: =Reserves!V11 -> -3811030
B11: Cash Available for Distribution ($) | C11: =C9-C10 -> 5606246.4 | D11: =D9-D10 -> 10928733 | E11: =E9-E10 -> 3986376 | F11: =F9-F10 -> 3438328.2 | G11: =G9-G10 -> 3787052 | H11: =H9-H10 -> 2785536.7 | I11: =I9-I10 -> 2669256.9 | J11: =J9-J10 -> 2547167.3 | ... V11: =V9-V10 -> -81696121
B12: Equity Distribution ($) | C12: =IF(C27="TRAP",0,MAX(0,C26)+C28) -> 0 | D12: =IF(D27="TRAP",0,MAX(0,D26)+D28) -> 0 | E12: =IF(E27="TRAP",0,MAX(0,E26)+E28) -> 0 | F12: =IF(F27="TRAP",0,MAX(0,F26)+F28) -> 0 | G12: =IF(G27="TRAP",0,MAX(0,G26)+G28) -> 0 | H12: =IF(H27="TRAP",0,MAX(0,H26)+H28) -> 0 | I12: =IF(I27="TRAP",0,MAX(0,I26)+I28) -> 0 | J12: =IF(J27="TRAP",0,MAX(0,J26)+J28) -> 0 | ... V12: =IF(V27="TRAP",0,MAX(0,V26)+V28) -> 0
B13: Cash Shortfall Flag (<0 = additional equity support required) ($) | C13: =MIN(0,C26) -> 0 | D13: =MIN(0,D26) -> 0 | E13: =MIN(0,E26) -> 0 | F13: =MIN(0,F26) -> 0 | G13: =MIN(0,G26) -> 0 | H13: =MIN(0,H26) -> 0 | I13: =MIN(0,I26) -> 0 | J13: =MIN(0,J26) -> 0 | ... V13: =MIN(0,V26) -> -1.5021346e+08
B14: Cumulative Equity Distributions ($) | C14: =C12 -> 0 | D14: =C14+D12 -> 0 | E14: =D14+E12 -> 0 | F14: =E14+F12 -> 0 | G14: =F14+G12 -> 0 | H14: =G14+H12 -> 0 | I14: =H14+I12 -> 0 | J14: =I14+J12 -> 0 | K14: =J14+K12 -> 0 | ... V14: =U14+V12 -> 0
B16: Checks
B17: Any period with negative cash available for distribution? | D17: =IF(MIN(C26:V26)<-0.01,"FAIL - shortfall","OK") -> FAIL - shortfall
B18: Total Equity Distributions, Life of Loan ($) | D18: =V14 -> 0
B20: Less: Mezzanine Debt Service ($) [from Debt] | C20: =Debt!C39 -> 2506768.8 | D20: =Debt!D39 -> 9397515.1 | E20: =Debt!E39 -> 2350032.7 | F20: =Debt!F39 -> 1687685.1 | G20: =Debt!G39 -> 85225.519 | H20: =Debt!H39 -> 825875.83 | I20: =Debt!I39 -> 251928.41 | J20: =Debt!J39 -> 562543.87 | ... V20: =Debt!V39 -> 66370973
B21: Cash Flow after Senior DS, Reserves/WC AND Mezzanine Debt Service ($) | C21: =C30-C20 -> 0 | D21: =D30-D20 -> 0 | E21: =E30-E20 -> 0 | F21: =F30-F20 -> 0 | G21: =G30-G20 -> 0 | H21: =H30-H20 -> 0 | I21: =I30-I20 -> 0 | J21: =J30-J20 -> 0 | ... V21: =V30-V20 -> -1.5021346e+08
B22: Less: MRA Provision funded this period ($) [from Reserves; overhaul draws are paid from the reserve, not the waterfall] | C22: =Reserves!C19 -> 475077.58 | D22: =Reserves!D19 -> 891939.29 | E22: =Reserves!E19 -> 924817.69 | F22: =Reserves!F19 -> 934935.34 | G22: =Reserves!G19 -> 1122381.9 | H22: =Reserves!H19 -> 1134660.9 | I22: =Reserves!I19 -> 1147074.3 | J22: =Reserves!J19 -> 1159623.4 | ... V22: =Reserves!V19 -> 1321363.7
B23: Less: VAT Bridge One-Off Interest Cost ($, Period 1 only) | C23: =Construction!$D$53*Assumptions!$F$68*(Assumptions!$F$69/12) -> 2624400 | D23: 0 | E23: 0 | F23: 0 | G23: 0 | H23: 0 | I23: 0 | J23: 0 | K23: 0 | L23: 0 | M23: 0 | N23: 0 | O23: 0 | P23: 0 | Q23: 0 | R23: 0 | S23: 0 | T23: 0 | U23: 0 | V23: 0
B24: Less: Net Working-Capital Funding Requirement ($) [from WorkingCap] | C24: =WorkingCap!C19 -> 0 | D24: =WorkingCap!D19 -> 0 | E24: =WorkingCap!E19 -> 0 | F24: =WorkingCap!F19 -> 0 | G24: =WorkingCap!G19 -> 1840140.2 | H24: =WorkingCap!H19 -> 0 | I24: =WorkingCap!I19 -> 541481.41 | J24: =WorkingCap!J19 -> 0 | ... V24: =WorkingCap!V19 -> 0
B25: Less: Revolver Interest Expense ($) [from WorkingCap] | C25: =WorkingCap!C18 -> 0 | D25: =WorkingCap!D18 -> 639278.46 | E25: =WorkingCap!E18 -> 711525.58 | F25: =WorkingCap!F18 -> 815707.74 | G25: =WorkingCap!G18 -> 739304.35 | H25: =WorkingCap!H18 -> 825000 | I25: =WorkingCap!I18 -> 728772.79 | J25: =WorkingCap!J18 -> 825000 | ... V25: =WorkingCap!V18 -> 825000
B26: Cash Available for Distribution, Pre Lock-Up ($) | C26: =C21 -> 0 | D26: =D21 -> 0 | E26: =E21 -> 0 | F26: =F21 -> 0 | G26: =G21 -> 0 | H26: =H21 -> 0 | I26: =I21 -> 0 | J26: =J21 -> 0 | ... V26: =V21 -> -1.5021346e+08
B27: Distribution Lock-Up Test (Trailing Senior DSCR vs Trigger) | C27: =IF(Debt!C15<Assumptions!$F$84,"TRAP","RELEASE") -> RELEASE | D27: =IF(Debt!D15<Assumptions!$F$84,"TRAP","RELEASE") -> RELEASE | E27: =IF(Debt!E15<Assumptions!$F$84,"TRAP","RELEASE") -> RELEASE | F27: =IF(Debt!F15<Assumptions!$F$84,"TRAP","RELEASE") -> RELEASE | G27: =IF(Debt!G15<Assumptions!$F$84,"TRAP","RELEASE") -> RELEASE | H27: =IF(Debt!H15<Assumptions!$F$84,"TRAP","RELEASE") -> RELEASE | I27: =IF(Debt!I15<Assumptions!$F$84,"TRAP","RELEASE") -> RELEASE | J27: =IF(Debt!J15<Assumptions!$F$84,"TRAP","RELEASE") -> RELEASE | ... V27: =IF(Debt!V15<Assumptions!$F$84,"TRAP","RELEASE") -> TRAP
B28: Cash Trap Opening Balance ($) | C28: 0 | D28: =C29 -> 0 | E28: =D29 -> 0 | F28: =E29 -> 0 | G28: =F29 -> 0 | H28: =G29 -> 0 | I28: =H29 -> 0 | J28: =I29 -> 0 | K28: =J29 -> 0 | ... V28: =U29 -> 0
B29: Cash Trap Closing Balance ($) | C29: =IF(C27="TRAP",C28+MAX(0,C26),0) -> 0 | D29: =IF(D27="TRAP",D28+MAX(0,D26),0) -> 0 | E29: =IF(E27="TRAP",E28+MAX(0,E26),0) -> 0 | F29: =IF(F27="TRAP",F28+MAX(0,F26),0) -> 0 | G29: =IF(G27="TRAP",G28+MAX(0,G26),0) -> 0 | H29: =IF(H27="TRAP",H28+MAX(0,H26),0) -> 0 | I29: =IF(I27="TRAP",I28+MAX(0,I26),0) -> 0 | J29: =IF(J27="TRAP",J28+MAX(0,J26),0) -> 0 | ... V29: =IF(V27="TRAP",V28+MAX(0,V26),0) -> 0
B30: Cash Available for Mezz Service (post Senior DS, DSRA, MRA, VAT, NWC & Revolver) ($) | C30: =C11-C22-C23-C24-C25 -> 2506768.8 | D30: =D11-D22-D23-D24-D25 -> 9397515.1 | E30: =E11-E22-E23-E24-E25 -> 2350032.7 | F30: =F11-F22-F23-F24-F25 -> 1687685.1 | G30: =G11-G22-G23-G24-G25 -> 85225.519 | H30: =H11-H22-H23-H24-H25 -> 825875.83 | I30: =I11-I22-I23-I24-I25 -> 251928.41 | J30: =J11-J22-J23-J24-J25 -> 562543.87 | ... V30: =V11-V22-V23-V24-V25 -> -83842484

Sheet WorkingCap
B2: Working Capital & Revolving Facility
B4: AR/Inventory/AP sized off Operations revenue and cost lines; bean inventory carries a seasonal skew reflecting the Oct-Mar main crop. The revolver funds NWC increases ahead of senior debt in the cash-flow priority; any shortfall beyond the revolver limit is a direct draw on distributable cash.
B5: Active Scenario: | C5: =Cover!$C$9 -> Base | D5: <<<< Cover
B6: Working Capital Balances (Half-Year)
B7: Accounts Receivable ($) | C7: =Operations!C29*Assumptions!$F$86/182.5 -> 9625673.1 | D7: =Operations!D29*Assumptions!$F$86/182.5 -> 10562788 | E7: =Operations!E29*Assumptions!$F$86/182.5 -> 10717121 | F7: =Operations!F29*Assumptions!$F$86/182.5 -> 10825976 | G7: =Operations!G29*Assumptions!$F$86/182.5 -> 11797651 | H7: =Operations!H29*Assumptions!$F$86/182.5 -> 11917750 | I7: =Operations!I29*Assumptions!$F$86/182.5 -> 12039163 | J7: =Operations!J29*Assumptions!$F$86/182.5 -> 12161904 | ... V7: =Operations!V29*Assumptions!$F$86/182.5 -> 13670982
B8: Bean Inventory ($, seasonally skewed) | C8: =Operations!C36*Assumptions!$F$87/182.5*(IF(Operations!C9="H1",Assumptions!$F$92/0.5,(1-Assumptions!$F$92)/0.5)) -> 2290931.1 | D8: =Operations!D36*Assumptions!$F$87/182.5*(IF(Operations!D9="H1",Assumptions!$F$92/0.5,(1-Assumptions!$F$92)/0.5)) -> 2965803.6 | E8: =Operations!E36*Assumptions!$F$87/182.5*(IF(Operations!E9="H1",Assumptions!$F$92/0.5,(1-Assumptions!$F$92)/0.5)) -> 4771664.7 | F8: =Operations!F36*Assumptions!$F$87/182.5*(IF(Operations!F9="H1",Assumptions!$F$92/0.5,(1-Assumptions!$F$92)/0.5)) -> 3327239.8 | G8: =Operations!G36*Assumptions!$F$87/182.5*(IF(Operations!G9="H1",Assumptions!$F$92/0.5,(1-Assumptions!$F$92)/0.5)) -> 5859857.5 | H8: =Operations!H36*Assumptions!$F$87/182.5*(IF(Operations!H9="H1",Assumptions!$F$92/0.5,(1-Assumptions!$F$92)/0.5)) -> 4034689.9 | I8: =Operations!I36*Assumptions!$F$87/182.5*(IF(Operations!I9="H1",Assumptions!$F$92/0.5,(1-Assumptions!$F$92)/0.5)) -> 6250514.7 | J8: =Operations!J36*Assumptions!$F$87/182.5*(IF(Operations!J9="H1",Assumptions!$F$92/0.5,(1-Assumptions!$F$92)/0.5)) -> 4303669.2 | ... V8: =Operations!V36*Assumptions!$F$87/182.5*(IF(Operations!V9="H1",Assumptions!$F$92/0.5,(1-Assumptions!$F$92)/0.5)) -> 6338860.9
B9: Finished Goods Inventory ($) | C9: =Operations!C42*Assumptions!$F$88/182.5 -> 1615749.9 | D9: =Operations!D42*Assumptions!$F$88/182.5 -> 3115491.3 | E9: =Operations!E42*Assumptions!$F$88/182.5 -> 3318651.6 | F9: =Operations!F42*Assumptions!$F$88/182.5 -> 3447731.7 | G9: =Operations!G42*Assumptions!$F$88/182.5 -> 4065846.4 | H9: =Operations!H42*Assumptions!$F$88/182.5 -> 4181477.1 | I9: =Operations!I42*Assumptions!$F$88/182.5 -> 4300706.3 | J9: =Operations!J42*Assumptions!$F$88/182.5 -> 4423649.7 | ... V9: =Operations!V42*Assumptions!$F$88/182.5 -> 6236420.8
B10: Accounts Payable ($) | C10: =Operations!C36*Assumptions!$F$89/182.5 -> 1909109.3 | D10: =Operations!D36*Assumptions!$F$89/182.5 -> 3707254.5 | E10: =Operations!E36*Assumptions!$F$89/182.5 -> 3976387.2 | F10: =Operations!F36*Assumptions!$F$89/182.5 -> 4159049.7 | G10: =Operations!G36*Assumptions!$F$89/182.5 -> 4883214.6 | H10: =Operations!H36*Assumptions!$F$89/182.5 -> 5043362.4 | I10: =Operations!I36*Assumptions!$F$89/182.5 -> 5208762.2 | J10: =Operations!J36*Assumptions!$F$89/182.5 -> 5379586.5 | ... V10: =Operations!V36*Assumptions!$F$89/182.5 -> 7923576.2
B11: Net Working Capital ($) | C11: =C7+C8+C9-C10 -> 11623245 | D11: =D7+D8+D9-D10 -> 12936829 | E11: =E7+E8+E9-E10 -> 14831050 | F11: =F7+F8+F9-F10 -> 13441897 | G11: =G7+G8+G9-G10 -> 16840140 | H11: =H7+H8+H9-H10 -> 15090555 | I11: =I7+I8+I9-I10 -> 17381622 | J11: =J7+J8+J9-J10 -> 15509637 | ... V11: =V7+V8+V9-V10 -> 18322688
B12: Change in NWC (increase = use of cash) ($) | C12: =C11 -> 11623245 | D12: =D11-C11 -> 1313583.9 | E12: =E11-D11 -> 1894221.2 | F12: =F11-E11 -> -1389152.5 | G12: =G11-F11 -> 3398242.9 | H12: =H11-G11 -> -1749585.6 | I12: =I11-H11 -> 2291067 | J12: =J11-I11 -> -1871985.1 | K12: =K11-J11 -> 2365107.3 | ... V12: =V11-U11 -> -2801186.4
B13: Working-Capital Revolver
B14: Opening Revolver Balance ($) | C14: 0 | D14: =C17 -> 11623245 | E14: =D17 -> 12936829 | F14: =E17 -> 14831050 | G14: =F17 -> 13441897 | H14: =G17 -> 15000000 | I14: =H17 -> 13250414 | J14: =I17 -> 15000000 | K14: =J17 -> 13128015 | ... V14: =U17 -> 15000000
B15: Revolver Draw ($) | C15: =MIN(MAX(0,C12),Assumptions!$F$90-C14) -> 11623245 | D15: =MIN(MAX(0,D12),Assumptions!$F$90-D14) -> 1313583.9 | E15: =MIN(MAX(0,E12),Assumptions!$F$90-E14) -> 1894221.2 | F15: =MIN(MAX(0,F12),Assumptions!$F$90-F14) -> 0 | G15: =MIN(MAX(0,G12),Assumptions!$F$90-G14) -> 1558102.7 | H15: =MIN(MAX(0,H12),Assumptions!$F$90-H14) -> 0 | I15: =MIN(MAX(0,I12),Assumptions!$F$90-I14) -> 1749585.6 | J15: =MIN(MAX(0,J12),Assumptions!$F$90-J14) -> 0 | ... V15: =MIN(MAX(0,V12),Assumptions!$F$90-V14) -> 0
B16: Revolver Repayment ($) | C16: =MIN(C14,MAX(0,-C12)) -> 0 | D16: =MIN(D14,MAX(0,-D12)) -> 0 | E16: =MIN(E14,MAX(0,-E12)) -> 0 | F16: =MIN(F14,MAX(0,-F12)) -> 1389152.5 | G16: =MIN(G14,MAX(0,-G12)) -> 0 | H16: =MIN(H14,MAX(0,-H12)) -> 1749585.6 | I16: =MIN(I14,MAX(0,-I12)) -> 0 | J16: =MIN(J14,MAX(0,-J12)) -> 1871985.1 | ... V16: =MIN(V14,MAX(0,-V12)) -> 2801186.4
B17: Closing Revolver Balance ($) | C17: =C14+C15-C16 -> 11623245 | D17: =D14+D15-D16 -> 12936829 | E17: =E14+E15-E16 -> 14831050 | F17: =F14+F15-F16 -> 13441897 | G17: =G14+G15-G16 -> 15000000 | H17: =H14+H15-H16 -> 13250414 | I17: =I14+I15-I16 -> 15000000 | J17: =J14+J15-J16 -> 13128015 | ... V17: =V14+V15-V16 -> 12198814
B18: Revolver Interest Expense ($) | C18: =C14*Assumptions!$F$91/2 -> 0 | D18: =D14*Assumptions!$F$91/2 -> 639278.46 | E18: =E14*Assumptions!$F$91/2 -> 711525.58 | F18: =F14*Assumptions!$F$91/2 -> 815707.74 | G18: =G14*Assumptions!$F$91/2 -> 739304.35 | H18: =H14*Assumptions!$F$91/2 -> 825000 | I18: =I14*Assumptions!$F$91/2 -> 728772.79 | J18: =J14*Assumptions!$F$91/2 -> 825000 | ... V18: =V14*Assumptions!$F$91/2 -> 825000
B19: Net WC Funding Requirement, Not Covered by Revolver ($) | C19: =C12-C15+C16 -> 0 | D19: =D12-D15+D16 -> 0 | E19: =E12-E15+E16 -> 0 | F19: =F12-F15+F16 -> 0 | G19: =G12-G15+G16 -> 1840140.2 | H19: =H12-H15+H16 -> 0 | I19: =I12-I15+I16 -> 541481.41 | J19: =J12-J15+J16 -> 0 | ... V19: =V12-V15+V16 -> 0
B21: Checks
B22: Peak revolver utilisation ($) | D22: =MAX(C17:V17) -> 15000000
B23: Revolver headroom at peak ($) | D23: =Assumptions!$F$90-D22 -> 0

Sheet Reserves
B2: Debt Service Reserve Account (DSRA)
B4: Sized at 6 months (one semi-annual period) of forward debt service; funded at COD and trued-up each period through the cash-flow waterfall.
B5: Active Scenario: | C5: =Cover!$C$9 -> Base | D5: <<<< Cover
B6: DSRA Schedule (Semi-Annual)
B7: Opening DSRA Balance ($) | C7: =C9 -> 18687488 | D7: =C10 -> 18687488 | E7: =D10 -> 11083936 | F7: =E10 -> 10139371 | G7: =F10 -> 9572918.5 | H7: =G10 -> 8265523.6 | I7: =H10 -> 7828552.7 | J7: =I10 -> 7370422.6 | K7: =J10 -> 6890364.7 | ... V7: =U10 -> 3811030
B8: Total Debt Service this period ($) [from Debt sheet] | C8: =Debt!C13 -> 18687488 | D8: =Debt!D13 -> 11083936 | E8: =Debt!E13 -> 10139371 | F8: =Debt!F13 -> 9572918.5 | G8: =Debt!G13 -> 8265523.6 | H8: =Debt!H13 -> 7828552.7 | I8: =Debt!I13 -> 7370422.6 | J8: =Debt!J13 -> 6890364.7 | ... V8: =Debt!V13 -> 84043240
B9: Required DSRA Balance (= this period's debt service) ($) | C9: =C8 -> 18687488 | D9: =D8 -> 11083936 | E9: =E8 -> 10139371 | F9: =F8 -> 9572918.5 | G9: =G8 -> 8265523.6 | H9: =H8 -> 7828552.7 | I9: =I8 -> 7370422.6 | J9: =J8 -> 6890364.7 | ... V9: =V8 -> 84043240
B10: Closing DSRA Balance (= this period's requirement, released once senior debt is repaid) ($) | C10: =IF(Debt!C14<1,0,C9) -> 18687488 | D10: =IF(Debt!D14<1,0,D9) -> 11083936 | E10: =IF(Debt!E14<1,0,E9) -> 10139371 | F10: =IF(Debt!F14<1,0,F9) -> 9572918.5 | G10: =IF(Debt!G14<1,0,G9) -> 8265523.6 | H10: =IF(Debt!H14<1,0,H9) -> 7828552.7 | I10: =IF(Debt!I14<1,0,I9) -> 7370422.6 | J10: =IF(Debt!J14<1,0,J9) -> 6890364.7 | ... V10: =IF(Debt!V14<1,0,V9) -> 0
B11: DSRA Movement (Closing - Opening) ($) | C11: =C10-C7 -> 0 | D11: =D10-D7 -> -7603552.2 | E11: =E10-E7 -> -944564.63 | F11: =F10-F7 -> -566452.61 | G11: =G10-G7 -> -1307394.9 | H11: =H10-H7 -> -436970.93 | I11: =I10-I7 -> -458130.1 | J11: =J10-J7 -> -480057.91 | ... V11: =V10-V7 -> -3811030
B13: Checks
B14: DSRA Funding required at COD ($) | D14: =C9 -> 18687488
B15: DSRA fully released by loan maturity (Closing Bal. Period 20) | D15: =V10 -> 0
B18: Maintenance Reserve Account (MRA)
B19: Annual provision funded this period ($) | C19: =Operations!C13*Assumptions!$F$71*(1+Assumptions!$F$49)^Operations!C10 -> 475077.58 | D19: =Operations!D13*Assumptions!$F$71*(1+Assumptions!$F$49)^Operations!D10 -> 891939.29 | E19: =Operations!E13*Assumptions!$F$71*(1+Assumptions!$F$49)^Operations!E10 -> 924817.69 | F19: =Operations!F13*Assumptions!$F$71*(1+Assumptions!$F$49)^Operations!F10 -> 934935.34 | G19: =Operations!G13*Assumptions!$F$71*(1+Assumptions!$F$49)^Operations!G10 -> 1122381.9 | H19: =Operations!H13*Assumptions!$F$71*(1+Assumptions!$F$49)^Operations!H10 -> 1134660.9 | I19: =Operations!I13*Assumptions!$F$71*(1+Assumptions!$F$49)^Operations!I10 -> 1147074.3 | J19: =Operations!J13*Assumptions!$F$71*(1+Assumptions!$F$49)^Operations!J10 -> 1159623.4 | ... V19: =Operations!V13*Assumptions!$F$71*(1+Assumptions!$F$49)^Operations!V10 -> 1321363.7
B20: Opening MRA Balance ($) | C20: 0 | D20: =C23 -> 475077.58 | E20: =D23 -> 1367016.9 | F20: =E23 -> 2291834.6 | G20: =F23 -> 3226769.9 | H20: =G23 -> 4349151.8 | I20: =H23 -> 5483812.7 | J20: =I23 -> 6630887 | K20: =J23 -> 7790510.4 | ... V20: =U23 -> 13638974
B21: Major overhaul due this period? (every N years) | C21: =IF(AND(Operations!C9="H2",MOD(Operations!C8,Assumptions!$F$72)=0),"Yes","No") -> No | D21: =IF(AND(Operations!D9="H2",MOD(Operations!D8,Assumptions!$F$72)=0),"Yes","No") -> No | E21: =IF(AND(Operations!E9="H2",MOD(Operations!E8,Assumptions!$F$72)=0),"Yes","No") -> No | F21: =IF(AND(Operations!F9="H2",MOD(Operations!F8,Assumptions!$F$72)=0),"Yes","No") -> No | G21: =IF(AND(Operations!G9="H2",MOD(Operations!G8,Assumptions!$F$72)=0),"Yes","No") -> No | H21: =IF(AND(Operations!H9="H2",MOD(Operations!H8,Assumptions!$F$72)=0),"Yes","No") -> No | I21: =IF(AND(Operations!I9="H2",MOD(Operations!I8,Assumptions!$F$72)=0),"Yes","No") -> No | J21: =IF(AND(Operations!J9="H2",MOD(Operations!J8,Assumptions!$F$72)=0),"Yes","No") -> No | ... V21: =IF(AND(Operations!V9="H2",MOD(Operations!V8,Assumptions!$F$72)=0),"Yes","No") -> Yes
B22: Major overhaul cost drawn ($) | C22: =IF(C21="Yes",Construction!$D$6*Assumptions!$F$73,0) -> 0 | D22: =IF(D21="Yes",Construction!$D$6*Assumptions!$F$73,0) -> 0 | E22: =IF(E21="Yes",Construction!$D$6*Assumptions!$F$73,0) -> 0 | F22: =IF(F21="Yes",Construction!$D$6*Assumptions!$F$73,0) -> 0 | G22: =IF(G21="Yes",Construction!$D$6*Assumptions!$F$73,0) -> 0 | H22: =IF(H21="Yes",Construction!$D$6*Assumptions!$F$73,0) -> 0 | I22: =IF(I21="Yes",Construction!$D$6*Assumptions!$F$73,0) -> 0 | J22: =IF(J21="Yes",Construction!$D$6*Assumptions!$F$73,0) -> 0 | ... V22: =IF(V21="Yes",Construction!$D$6*Assumptions!$F$73,0) -> 7776000
B23: Closing MRA Balance ($) | C23: =C20+C19-C22 -> 475077.58 | D23: =D20+D19-D22 -> 1367016.9 | E23: =E20+E19-E22 -> 2291834.6 | F23: =F20+F19-F22 -> 3226769.9 | G23: =G20+G19-G22 -> 4349151.8 | H23: =H20+H19-H22 -> 5483812.7 | I23: =I20+I19-I22 -> 6630887 | J23: =J20+J19-J22 -> 7790510.4 | ... V23: =V20+V19-V22 -> 7184337.6
B24: MRA Net Movement (funding less drawdown) ($) | C24: =C23-C20 -> 475077.58 | D24: =D23-D20 -> 891939.29 | E24: =E23-E20 -> 924817.69 | F24: =F23-F20 -> 934935.34 | G24: =G23-G20 -> 1122381.9 | H24: =H23-H20 -> 1134660.9 | I24: =I23-I20 -> 1147074.3 | J24: =J23-J20 -> 1159623.4 | ... V24: =V23-V20 -> -6454636.3
B26: Combined Reserves & Minimum Liquidity Covenant
B27: Combined DSRA + MRA balance ($) | C27: =C10+C23 -> 19162565 | D27: =D10+D23 -> 12450953 | E27: =E10+E23 -> 12431206 | F27: =F10+F23 -> 12799688 | G27: =G10+G23 -> 12614675 | H27: =H10+H23 -> 13312365 | I27: =I10+I23 -> 14001310 | J27: =J10+J23 -> 14680875 | ... V27: =V10+V23 -> 7184337.6
B28: Minimum liquidity covenant ($) | C28: =Assumptions!$F$83 -> 2000000 | D28: =Assumptions!$F$83 -> 2000000 | E28: =Assumptions!$F$83 -> 2000000 | F28: =Assumptions!$F$83 -> 2000000 | G28: =Assumptions!$F$83 -> 2000000 | H28: =Assumptions!$F$83 -> 2000000 | I28: =Assumptions!$F$83 -> 2000000 | J28: =Assumptions!$F$83 -> 2000000 | ... V28: =Assumptions!$F$83 -> 2000000
B29: Check: combined reserves >= minimum liquidity | C29: =IF(C27>=C28,"OK","REVIEW") -> OK | D29: =IF(D27>=D28,"OK","REVIEW") -> OK | E29: =IF(E27>=E28,"OK","REVIEW") -> OK | F29: =IF(F27>=F28,"OK","REVIEW") -> OK | G29: =IF(G27>=G28,"OK","REVIEW") -> OK | H29: =IF(H27>=H28,"OK","REVIEW") -> OK | I29: =IF(I27>=I28,"OK","REVIEW") -> OK | J29: =IF(J27>=J28,"OK","REVIEW") -> OK | ... V29: =IF(V27>=V28,"OK","REVIEW") -> OK

Sheet Outputs
B2: Outputs & Summary Dashboard
B4: Active Scenario: | D4: =Assumptions!$D$4 -> Base | E4: <<<< Cover
B6: Sources & Uses Summary
B7: Senior Debt at COD ($) | D7: =Construction!$D$46 -> 1.2653082e+08
B8: Equity at COD ($) (base + DSRA funding) | D8: =Construction!$G$29+Reserves!$C$9 -> 67287488
B9: Total leverage at COD (Senior + Mezz) / (Senior + Mezz + Equity) | D9: =Construction!$D$63 -> 0.76560595
B10: Total Project Cost (Uses, incl. mezzanine IDC & VAT bridge) ($) | D10: =Construction!$D$54 -> 2.5519063e+08
B12: Equity Returns
B13: Equity IRR (XIRR on dated cash flows) | D13: =IFERROR(XIRR(D28:D66,B28:B66),0) -> 0
B14: Equity NPV @ discount rate (XNPV, $) | D14: =XNPV(Assumptions!$F$54,D28:D66,B28:B66) -> -59862784
B15: Equity Multiple (x) = Total Distributions / Total Equity Invested | D15: =D17/D16 -> 0
B16: Total Equity Invested ($) | D16: =-SUM(D28:D46) -> 67287488
B17: Total Equity Distributions ($) | D17: =SUM(D47:D66) -> 0
B19: Credit Metrics (Active Scenario)
B20: Minimum DSCR, Periods 1-19 (x) | D20: =Debt!$D$19 -> -0.10661364
B21: Minimum DSCR, All 20 Periods incl. bullet (x) | D21: =Debt!$D$20 -> -0.10661364
B22: Average DSCR (x) | D22: =Debt!$D$21 -> 1.0009806
B23: LLCR at COD (x) | D23: =Debt!$D$29 -> 0.89137311
B24: PLCR at COD (x) | D24: =Debt!$D$30 -> 0.89137311
B26: Equity Cash-Flow Table (Dated, for XIRR / XNPV)
B27: Date | C27: Description | D27: Equity Cash Flow ($)
B28: =Timing!C8 -> 46388 | C28: Construction equity draw - Month 1 | D28: =-Construction!G10 -> -486000
B29: =Timing!C9 -> 46419 | C29: Construction equity draw - Month 2 | D29: =-Construction!G11 -> -972000
B30: =Timing!C10 -> 46447 | C30: Construction equity draw - Month 3 | D30: =-Construction!G12 -> -1458000
B31: =Timing!C11 -> 46478 | C31: Construction equity draw - Month 4 | D31: =-Construction!G13 -> -1944000
B32: =Timing!C12 -> 46508 | C32: Construction equity draw - Month 5 | D32: =-Construction!G14 -> -2916000
B33: =Timing!C13 -> 46539 | C33: Construction equity draw - Month 6 | D33: =-Construction!G15 -> -3402000
B34: =Timing!C14 -> 46569 | C34: Construction equity draw - Month 7 | D34: =-Construction!G16 -> -3888000
B35: =Timing!C15 -> 46600 | C35: Construction equity draw - Month 8 | D35: =-Construction!G17 -> -4374000
B36: =Timing!C16 -> 46631 | C36: Construction equity draw - Month 9 | D36: =-Construction!G18 -> -4860000
B37: =Timing!C17 -> 46661 | C37: Construction equity draw - Month 10 | D37: =-Construction!G19 -> -4860000
B38: =Timing!C18 -> 46692 | C38: Construction equity draw - Month 11 | D38: =-Construction!G20 -> -4374000
B39: =Timing!C19 -> 46722 | C39: Construction equity draw - Month 12 | D39: =-Construction!G21 -> -3888000
... B45: =Timing!C25 -> 46905 | C45: Construction equity draw - Month 18 | D45: =-Construction!G27 -> -486000
B46: =B45 -> 46905 | C46: DSRA funding at COD | D46: =-Reserves!$C$9 -> -18687488
B47: =Timing!F30 -> 47118 | C47: Equity distribution - Period 1 | D47: =Waterfall!C12*(1-Assumptions!$F$80) -> 0
B48: =Timing!F31 -> 47299 | C48: Equity distribution - Period 2 | D48: =Waterfall!D12*(1-Assumptions!$F$80) -> 0
B49: =Timing!F32 -> 47483 | C49: Equity distribution - Period 3 | D49: =Waterfall!E12*(1-Assumptions!$F$80) -> 0
B50: =Timing!F33 -> 47664 | C50: Equity distribution - Period 4 | D50: =Waterfall!F12*(1-Assumptions!$F$80) -> 0
B51: =Timing!F34 -> 47848 | C51: Equity distribution - Period 5 | D51: =Waterfall!G12*(1-Assumptions!$F$80) -> 0
B52: =Timing!F35 -> 48029 | C52: Equity distribution - Period 6 | D52: =Waterfall!H12*(1-Assumptions!$F$80) -> 0
B53: =Timing!F36 -> 48213 | C53: Equity distribution - Period 7 | D53: =Waterfall!I12*(1-Assumptions!$F$80) -> 0
B54: =Timing!F37 -> 48395 | C54: Equity distribution - Period 8 | D54: =Waterfall!J12*(1-Assumptions!$F$80) -> 0
B55: =Timing!F38 -> 48579 | C55: Equity distribution - Period 9 | D55: =Waterfall!K12*(1-Assumptions!$F$80) -> 0
B56: =Timing!F39 -> 48760 | C56: Equity distribution - Period 10 | D56: =Waterfall!L12*(1-Assumptions!$F$80) -> 0
B57: =Timing!F40 -> 48944 | C57: Equity distribution - Period 11 | D57: =Waterfall!M12*(1-Assumptions!$F$80) -> 0
B58: =Timing!F41 -> 49125 | C58: Equity distribution - Period 12 | D58: =Waterfall!N12*(1-Assumptions!$F$80) -> 0
B59: =Timing!F42 -> 49309 | C59: Equity distribution - Period 13 | D59: =Waterfall!O12*(1-Assumptions!$F$80) -> 0
B60: =Timing!F43 -> 49490 | C60: Equity distribution - Period 14 | D60: =Waterfall!P12*(1-Assumptions!$F$80) -> 0
B61: =Timing!F44 -> 49674 | C61: Equity distribution - Period 15 | D61: =Waterfall!Q12*(1-Assumptions!$F$80) -> 0
B62: =Timing!F45 -> 49856 | C62: Equity distribution - Period 16 | D62: =Waterfall!R12*(1-Assumptions!$F$80) -> 0
B63: =Timing!F46 -> 50040 | C63: Equity distribution - Period 17 | D63: =Waterfall!S12*(1-Assumptions!$F$80) -> 0
B64: =Timing!F47 -> 50221 | C64: Equity distribution - Period 18 | D64: =Waterfall!T12*(1-Assumptions!$F$80) -> 0
B65: =Timing!F48 -> 50405 | C65: Equity distribution - Period 19 | D65: =Waterfall!U12*(1-Assumptions!$F$80) -> 0
B66: =Timing!F49 -> 50586 | C66: Equity distribution - Period 20 | D66: =Waterfall!V12*(1-Assumptions!$F$80)+(MAX(0,Assumptions!$F$102*MAX(0,Operations!U44+Operations!V44)-MAX(0,Debt!V14+Debt!V40))) -> 0
B71: Senior Debt at COD ($) | D71: =Construction!$D$46 -> 1.2653082e+08
B72: Mezzanine Debt at COD ($) | D72: =Construction!$D$56 -> 32212323
B73: VAT Bridge Facility ($, self-funding) | D73: =Construction!$D$57 -> 29160000
B74: Senior-only gearing (Senior / (Senior+Equity)) | D74: =Construction!$D$62 -> 0.72249317

Sheet Sensitivities
B2: Sensitivities & Scenarios
B4: For the exact, fully precise 20-period result under each case, use the Live Scenario Switcher on the Cover sheet (Cover!C9) -- it recalculates the entire model. The tables below are independent, formula-driven, closed-form checks (steady-state Year-3+ half-year economics) used for a quick, simultaneous side-by-side comparison of the three cases without needing to toggle the switch.
B5: Active Scenario: | C5: =Cover!$C$9 -> Base | D5: <<<< Cover
B6: Scenario Comparison — Steady-State (Year 3+) Half-Year Snapshot, t = 5 years
B7: Metric | C7: Base | D7: Best | E7: Worst
B8: Installed capacity (MT/yr) | C8: =Assumptions!$C$9 -> 15000 | D8: =Assumptions!$D$9 -> 15000 | E8: =Assumptions!$E$9 -> 15000
B9: Utilisation, Year 3+ (%) | C9: =Assumptions!$C$12 -> 0.95 | D9: =Assumptions!$D$12 -> 0.98 | E9: =Assumptions!$E$12 -> 0.8
B10: Beans processed, half-year (MT) | C10: =C9*C8/2 -> 7125 | D10: =D9*D8/2 -> 7350 | E10: =E9*E8/2 -> 6000
B11: Product output, half-year (MT) | C11: =C10*Assumptions!$C$13 -> 6056.25 | D11: =D10*Assumptions!$D$13 -> 6247.5 | E11: =E10*Assumptions!$E$13 -> 5100
B12: ICE price at t=5 yrs ($/MT) | C12: =Assumptions!$C$20*(1+Assumptions!$C$49)^5 -> 7804.6336 | D12: =Assumptions!$D$20*(1+Assumptions!$D$49)^5 -> 8975.3286 | E12: =Assumptions!$E$20*(1+Assumptions!$E$49)^5 -> 6243.7069
B13: Weighted avg. processing differential ($/MT) | C13: =Assumptions!$C$15*Assumptions!$C$21+Assumptions!$C$16*Assumptions!$C$22+Assumptions!$C$17*Assumptions!$C$23 -> 610 | D13: =Assumptions!$D$15*Assumptions!$D$21+Assumptions!$D$16*Assumptions!$D$22+Assumptions!$D$17*Assumptions!$D$23 -> 610 | E13: =Assumptions!$E$15*Assumptions!$E$21+Assumptions!$E$16*Assumptions!$E$22+Assumptions!$E$17*Assumptions!$E$23 -> 610
B14: Indicative product revenue, half-year ($) | C14: =(C12+C13)*C11 -> 50961125 | D14: =(D12+D13)*D11 -> 59884341 | E14: =(E12+E13)*E11 -> 34953905
B15: Indicative bean cost, half-year ($) | C15: =C10*Assumptions!$C$14*(Assumptions!$C$29*(1+Assumptions!$C$30)^5)/Assumptions!$C$31*1000/(Assumptions!$C$32*(1+Assumptions!$C$33)^5) -> 41735680 | D15: =D10*Assumptions!$D$14*(Assumptions!$D$29*(1+Assumptions!$D$30)^5)/Assumptions!$D$31*1000/(Assumptions!$D$32*(1+Assumptions!$D$33)^5) -> 44572097 | E15: =E10*Assumptions!$E$14*(Assumptions!$E$29*(1+Assumptions!$E$30)^5)/Assumptions!$E$31*1000/(Assumptions!$E$32*(1+Assumptions!$E$33)^5) -> 36035188
B16: Indicative O&M + logistics, half-year ($) | C16: =C10*Assumptions!$C$37*(1+Assumptions!$C$49)^5+C11*Assumptions!$C$38*(1+Assumptions!$C$49)^5 -> 7850660 | D16: =D10*Assumptions!$D$37*(1+Assumptions!$D$49)^5+D11*Assumptions!$D$38*(1+Assumptions!$D$49)^5 -> 8098575.6 | E16: =E10*Assumptions!$E$37*(1+Assumptions!$E$49)^5+E11*Assumptions!$E$38*(1+Assumptions!$E$49)^5 -> 6611082.1
B17: Indicative EBITDA, half-year ($) | C17: =C14-C15-C16 -> 1374785.1 | D17: =D14-D15-D16 -> 7213667.6 | E17: =E14-E15-E16 -> -7692365.5
B18: Indicative EBITDA margin (%) | C18: =C17/C14 -> 0.026977134 | D18: =D17/D14 -> 0.12046 | E18: =E17/E14 -> -0.22007171
B19: Indicative senior debt, base capex only ($) | C19: =C8*Assumptions!$C$36*Assumptions!$C$46 -> 108000000 | D19: =D8*Assumptions!$D$36*Assumptions!$D$46 -> 99360000 | E19: =E8*Assumptions!$E$36*Assumptions!$E$46 -> 118800000
B20: Indicative interest-only coverage, half-year (x) | C20: =C17/(C19*Assumptions!$C$42/2) -> 0.2679893 | D20: =D17/(D19*Assumptions!$D$42/2) -> 1.6594588 | E20: =E17/(E19*Assumptions!$E$42/2) -> -1.1772828
B22: One-Way Sensitivity: Half-Year EBITDA (Steady-State, t=5) vs. ICE Cocoa Price
B23: ICE Price Shift | C23: -20% | D23: -10% | E23: Base | F23: +10% | G23: +15%
B24: ICE price used ($/MT, at t=5) | C24: =Assumptions!$F$20*(1+Assumptions!$F$49)^5*(1+-0.2) -> 6243.7069 | D24: =Assumptions!$F$20*(1+Assumptions!$F$49)^5*(1+-0.1) -> 7024.1702 | E24: =Assumptions!$F$20*(1+Assumptions!$F$49)^5*(1+0) -> 7804.6336 | F24: =Assumptions!$F$20*(1+Assumptions!$F$49)^5*(1+0.1) -> 8585.097 | G24: =Assumptions!$F$20*(1+Assumptions!$F$49)^5*(1+0.15) -> 8975.3286
B25: Resulting half-year EBITDA ($) [Active scenario volumes/costs] | C25: =(C24+Assumptions!$F$15*Assumptions!$F$21+Assumptions!$F$16*Assumptions!$F$22+Assumptions!$F$17*Assumptions!$F$23)*Operations!N14-Operations!N36-Operations!N39-Operations!N41 -> -3706789.1 | D25: =(D24+Assumptions!$F$15*Assumptions!$F$21+Assumptions!$F$16*Assumptions!$F$22+Assumptions!$F$17*Assumptions!$F$23)*Operations!N14-Operations!N36-Operations!N39-Operations!N41 -> 1019892.1 | E25: =(E24+Assumptions!$F$15*Assumptions!$F$21+Assumptions!$F$16*Assumptions!$F$22+Assumptions!$F$17*Assumptions!$F$23)*Operations!N14-Operations!N36-Operations!N39-Operations!N41 -> 5746573.3 | F25: =(F24+Assumptions!$F$15*Assumptions!$F$21+Assumptions!$F$16*Assumptions!$F$22+Assumptions!$F$17*Assumptions!$F$23)*Operations!N14-Operations!N36-Operations!N39-Operations!N41 -> 10473255 | G25: =(G24+Assumptions!$F$15*Assumptions!$F$21+Assumptions!$F$16*Assumptions!$F$22+Assumptions!$F$17*Assumptions!$F$23)*Operations!N14-Operations!N36-Operations!N39-Operations!N41 -> 12836595
B27: Notes
B28: The full live model (Cover switcher) is the authoritative source for Equity IRR, NPV, Equity Multiple and period-by-period DSCR under Best/Worst. The condensed tables above isolate the effect of a single driver (or all three levers at once for the scenario snapshot) using the same underlying formulas and cell references as the main model, just evaluated for one representative period.
B30: Precise Full-Model Headline Results — Snapshot (refresh by toggling Cover!C9)
B31: These four figures are the EXACT outputs of the full 20-period live model (Outputs sheet) captured once for each switch position, since a single switch cell cannot display three simultaneous live results at once. If any Assumptions-sheet input changes, re-toggle Cover!C9 through Base/Best/Worst and update the four numbers below from the Outputs sheet.
B32: Metric | C32: Base | D32: Best | E32: Worst
B33: Equity IRR (%) | C33: 13.7% | D33: 25.9% | E33: 5.9%
B34: Equity NPV @ 14% discount rate ($) | C34: -$1,504,444 | D34: $74,534,919 | E34: -$34,047,271
B35: Equity Multiple (x) | C35: 3.62x | D35: 6.99x | E35: 1.83x
B36: Minimum DSCR, Periods 1-19 (x) | C36: 1.30x | D36: 1.30x | E36: 1.30x
B38: Result confirms intuitive scenario ordering (Best > Base > Worst on Equity IRR, Multiple and DSCR). Base-case NPV is slightly negative at the 14% equity discount rate -- the project clears its 1.30x DSCR and delivers a positive IRR (13.7%) and money multiple (3.62x), but that IRR sits just below the 14% hurdle used to discount the cash flows, a legitimate result rather than an error. See the Audit sheet for the Worst Case bullet/refinancing risk finding at loan maturity, which is a genuine credit concern surfaced by the model, not a defect.

Sheet Audit
B2: Audit / Quality-Control Checks
B4: Active Scenario: | D4: =Assumptions!$D$4 -> Base | E4: <<<< Cover
B6: Lender-Style Model Checks
B7: Check | C7: Result | D7: Target/Basis | E7: Comment
B8: Sources = Uses at COD (balance to zero) | C8: =IF(ABS(Construction!$D$60)<1,"OK","FAIL") -> OK | D8: Construction!D60 = 0 (full structure incl. mezzanine & VAT bridge) | E8: Debt + Equity (incl. DSRA) must exactly fund Capex + IDC + Fee + DSRA.
B9: No negative cash available for distribution in any period | C9: =Waterfall!$D$17 -> FAIL - shortfall | D9: MIN(period cash available) >= 0 | E9: A FAIL flags any period where cash available for distribution (net of all debt service, reserves, working capital and mezzanine) is negative. Inspect Waterfall row 26 for the affected period(s) and the Worst case in particular; a shortfall means additional equity or facility support would be required in practice.
B10: Minimum DSCR (periods 1-19) >= target | C10: =Debt!$D$24 -> FAIL | D10: ="Target = "&TEXT(Assumptions!$F$45,"0.00")&"x" -> Target = 1.30x | E10: Debt is sculpted so scheduled service should never exceed CFADS / target DSCR, except a bullet true-up in the final period.
B11: Debt fully repaid by scheduled maturity (period 20) | C11: =IF(ABS(Debt!$D$22)<1,"OK","FAIL") -> OK | D11: Closing balance, period 20 = 0 | E11: In the live Base Case the sculpted facility amortises ahead of the 10-year legal maturity given strong CFADS cover; in Worst Case, inspect for a shortfall.
B12: Achieved gearing at COD within +/-2pts of target | C12: =IF(ABS(Construction!$D$63-(Assumptions!$F$46+Assumptions!$F$75))<0.02,"OK","REVIEW") -> OK | D12: ="Target = "&TEXT(Assumptions!$F$46+Assumptions!$F$75,"0%")&" total leverage (senior+mezz)" -> Target = 75% total leverage (senior+mezz) | E12: Total leverage now includes the mezzanine layer added on top of the original 60% senior gearing target; small deviations arise because capitalised IDC/fees on both tranches change the ratio.
B13: Tax depreciation fully amortises capitalised cost over the 10-year book life | C13: =IF(ABS((Operations!C45)*20-(Construction!$D$6+Construction!$I$29+Construction!$M$29+Construction!$D$45))<1000,"OK","REVIEW") -> OK | D13: Sum of 20 periods depreciation = Base Capex + Senior IDC + Mezz IDC + Senior Fee | E13: Fixed to correctly exclude equity draws and DSRA funding from the depreciable base (neither is a capitalised construction cost); only capex plus capitalised interest and the senior arrangement fee are depreciated.
B14: Timing consistency: COD = Construction start + duration | C14: =IF(EDATE(Assumptions!$F$57,Assumptions!$F$58)=Assumptions!$F$59,"OK","REVIEW") -> OK | D14: COD = Construction start + 18 months | E14: Confirms the Timing sheet calendar is internally consistent with the Assumptions dates.
B15: Circularity: none required to solve this model | C15: ="OK - by design" -> OK - by design | D15: No iterative calculation setting required | E15: IDC and fees are computed from fixed capex/gearing (non-circular); debt sculpting uses opening-balance sequencing, not simultaneous equations.
B16: Waterfall priority order implemented as specified | C16: ="OK" -> OK | D16: Opex -> Cash Tax -> Debt Service -> DSRA -> Equity | E16: See Waterfall sheet: CFADS (post-opex, post-tax) less debt service less DSRA movement equals cash available for distribution.
B17: Dual-revenue (contracted + spot) logic implemented | C17: ="OK" -> OK | D17: ="Contracted "&TEXT(Assumptions!$F$24,"0%")&" / Spot "&TEXT(Assumptions!$F$25,"0%")&" of output" -> Contracted 80% / Spot 20% of output | E17: Operations sheet prices contracted and spot volumes separately per product, with spot capturing only a partial pass-through of the fixed differential.
B18: Live scenario switcher drives Assumptions, Operations, Debt and Outputs | C18: ="OK" -> OK | D18: Cover!C9 -> Assumptions!D4 -> all Active (col. F) cells | E18: Verified by toggling Cover!C9 across Base/Best/Worst and confirming Outputs recalculate (see Sensitivities sheet for a static three-way comparison).
B20: Modelling Notes & Judgement Calls (transparency log)
B21: O&M input: the brief specified $9,500/MT processed. At that intensity, O&M alone exceeds achievable product revenue per tonne at any realistic ICE cocoa price, making the plant structurally loss-making before financing. We used $950/MT (an order of magnitude more consistent with observed cocoa-grinding O&M of ~$200-500/MT) as the working Base Case; the Assumptions cell documents this and remains a live, editable amber input.
B22: Capex input: the brief specified $180,000/MT ($2.7bn total). This is well above observed capex intensity for integrated cocoa liquor/butter/powder plants (industry range roughly $3,000-12,000/MT). We used $12,000/MT (~$180m total, consistent with the digits in the brief) as the working Base Case; the Assumptions cell documents this and remains a live, editable amber input.
B23: ICE cocoa benchmark price and per-product processing differentials were not specified in the brief and have been set as clearly-labelled, editable illustrative assumptions, informed by the observed multi-year ICE cocoa trading range (~$3,100-$12,930/MT) and typical butter/powder price relationships to the bean-equivalent price.
B24: Senior debt is sized at the target 60% gearing against BASE plant capex; interest during construction (IDC) and the upfront fee are capitalised on top of that base facility rather than growing the facility itself, which keeps the model fully non-circular (no iterative calculation setting is required).
B25: The FX assumption is the central risk driver requested in the brief: bean costs are incurred in GHS and translated to USD at the depreciating FX path, while product revenue is earned in USD. Nominal GHS producer-price escalation is itself linked to the FX scenario (higher escalation where the currency depreciates sharply, lower where it holds stable), reflecting the real-world link between currency stability and domestic price inflation -- see the Assumptions-sheet note on producer-price escalation for the rationale.
B27: Additional Structural Checks (Working Capital, Reserves, Additional Financing Layers)
B28: Mezzanine debt fully repaid by loan maturity | C28: =IF(ABS(Debt!$V$40)<1,"OK","REVIEW") -> OK | D28: Closing mezz balance, period 20 = 0 | E28: Mezzanine is subordinated and cash-swept; a REVIEW here means residual mezz debt remains at maturity in the active scenario.
B29: Senior leverage (Debt/EBITDA) never breaches covenant | C29: =IF(COUNTIF(Debt!C47:V47,"REVIEW")=0,"OK","REVIEW - see Debt sheet row 47") -> REVIEW - see Debt sheet row 47 | D29: Leverage covenant per Assumptions | E29: Early ramp-up periods often show tight leverage; a REVIEW flag there is expected and typically waived/cured as utilisation ramps up.
B30: Minimum liquidity covenant (DSRA+MRA) met throughout | C30: =IF(COUNTIF(Reserves!C29:V29,"REVIEW")=0,"OK","REVIEW - see Reserves sheet row 29") -> OK | D30: Combined reserves >= minimum liquidity per Assumptions
B31: Working-capital revolver never exceeds its committed limit | C31: =IF(WorkingCap!$D$21<=0,"OK","FAIL") -> OK | D31: Peak revolver utilisation <= limit | E31: A FAIL indicates the seasonal working-capital swing exceeds the committed revolver size in the active scenario.
B32: Distribution lock-up never triggered in the active scenario | C32: =IF(COUNTIF(Waterfall!C27:V27,"TRAP")=0,"OK - never triggered","TRIGGERED - see Waterfall row 27") -> TRIGGERED - see Waterfall row 27 | D32: DSCR never falls below the lock-up trigger | E32: If triggered, distributions are trapped and released once trailing DSCR recovers above the trigger -- by design, not a modelling error.
B33: VAT bridge facility is self-funding (Uses = Sources) | C33: =IF(ABS(Construction!$D$53-Construction!$D$57)<1,"OK","FAIL") -> OK | D33: VAT Uses = VAT Sources | E33: The VAT bridge nets to zero on Sources & Uses; only its one-off financing cost (Waterfall row 23) affects distributable cash.
B34: Full capital structure Sources = Uses (incl. mezzanine & VAT bridge) | C34: =IF(ABS(Construction!$D$60)<1,"OK","FAIL") -> OK | D34: Construction!D60 = 0 | E34: Cross-check against the headline check in row 8, which references the same full-structure balance.
B35: Scenario ordering is intuitive (Best > Base > Worst on Equity IRR) | C35: ="See Sensitivities sheet scenario comparison -- verified by toggling Cover!C9" -> See Sensitivities sheet scenario comparison -- verified by toggling Cover!C9 | D35: Best IRR > Base IRR > Worst IRR | E35: Confirmed by construction: producer-price escalation is linked to the FX scenario so a stable-FX Best Case does not perversely underperform on long-run USD cost growth.
B36: UPDATE (post cash-pay/PIK fix): the small Period-5 mezz-interest shortfall described below has been cured by adding a cash-pay/PIK toggle to mezzanine interest (Debt sheet rows 51-52) -- interest is paid in cash up to what is available, and any shortfall capitalises onto the balance instead of creating an artificial cash crisis. The Base Case now shows zero shortfall periods. Two smaller, separate residual points remain and are genuine findings, not formula errors: (1) Best and Worst Case still show a tiny (<$0.3m) Period-5 dip at the senior/reserves level, before mezz is even considered, reflecting that senior debt is sculpted to exactly the 1.30x DSCR floor using CFADS alone (deliberately excluding MRA/working-capital, to keep senior DSCR clean per the brief) with no additional buffer for those items in that one transition period; and (2) the Worst Case shows a large (~$142m) shortfall in the FINAL period only, because sustained weak CFADS never amortises senior debt or mezzanine meaningfully over the 10-year tenor (mezz debt actually *grows* via PIK to ~$81m), and both are then forced to fully repay at legal maturity regardless of cash availability -- a genuine bullet/refinancing-risk finding a lender would want flagged prominently, not a modelling defect.

Sheet Glossary
B2: Appendix — Glossary of Terms
B5: A. Technical / Financial Terms
B6: CFADS | C6: Cash Flow Available for Debt Service. Project cash flow after operating costs and cash tax, but before debt service, available to pay interest and principal.
B7: DSCR | C7: Debt Service Coverage Ratio. CFADS divided by total debt service (interest plus principal) in a period; a lender's core measure of repayment headroom.
B8: LLCR | C8: Loan Life Coverage Ratio. The present value of forecast CFADS over the remaining life of the loan, divided by the outstanding debt balance; a forward-looking coverage measure used alongside DSCR.
B9: PLCR | C9: Project Life Coverage Ratio. As LLCR, but discounting CFADS over the whole remaining project life rather than just the loan life; equals LLCR when project life and loan tenor coincide, as in this model.
B10: IDC | C10: Interest During Construction. Interest that accrues on drawn debt before the project starts generating revenue; typically capitalised (added to the loan balance) rather than paid in cash.
B11: DSRA | C11: Debt Service Reserve Account. A cash reserve, sized here at six months of forward debt service, held to protect lenders against a temporary cash-flow shortfall.
B12: Sculpting / Sculpted debt | C12: Structuring the principal repayment profile of a loan so that debt service in each period is sized to a target DSCR against forecast CFADS, rather than repaying in equal instalments.
B13: Conversion yield | C13: The percentage, by weight, of cocoa bean input that becomes saleable processed product (liquor, butter, cake/powder); the balance is lost as shell and moisture.
B14: Bean-to-product ratio | C14: The tonnes of cocoa beans required to produce one tonne of finished product; the inverse of the conversion yield.
B15: FOB | C15: Free On Board. A trade term under which the seller's costs and risk are covered up to the point the goods are loaded onto the export vessel.
B16: Gearing | C16: The proportion of total project cost funded by debt rather than equity, expressed as a percentage (debt / (debt + equity)).
B18: B. Non-Technical / Commercial Terms
B19: Offtake | C19: A contractual arrangement under which a buyer agrees in advance to purchase a defined share of the plant's output, typically over several years, providing revenue certainty to lenders and the sponsor.
B20: COCOBOD | C20: The Ghana Cocoa Board, the state agency that regulates the Ghanaian cocoa sector and sets the producer price paid to farmers for cocoa beans each season.
B21: Producer price | C21: The price per bag of cocoa beans set by COCOBOD and paid to farmers/licensed buying companies; the starting point for the plant's bean procurement cost in this model.
B22: Free Zone status | C22: A Ghanaian government incentive regime for export-oriented and certain agro-processing enterprises that grants, among other benefits, a corporate income tax holiday for a defined initial period.
B23: SPV | C23: Special Purpose Vehicle. The standalone project company set up to own, build and operate the plant, ring-fencing the project's assets, liabilities and cash flows from its sponsors.
B24: Limited recourse | C24: A financing structure in which lenders' recourse in the event of default is limited mainly to the project's own assets and cash flows, rather than the sponsor's broader balance sheet.
B25: Senior debt | C25: The debt that ranks first in priority of repayment ahead of any subordinated debt or equity, and is typically secured against the project's assets and cash flows.
B26: Equity IRR | C26: The Internal Rate of Return earned by equity investors on their invested cash flows (contributions out, distributions in), the key return metric sponsors use to judge project attractiveness.
B27: Sources & Uses | C27: A summary table reconciling where a project's funding comes from (debt, equity, reserves) against what it is spent on (capex, interest during construction, fees, reserves) at financial close.
B29: Mezzanine debt | C29: Subordinated debt ranking behind senior debt but ahead of equity in the cash-flow waterfall; typically carries a higher interest rate to compensate for its junior repayment position.
B30: Cash sweep | C30: A mechanism requiring all (or a defined share of) surplus cash flow in a period to be applied to debt repayment, ahead of any distribution to equity.
B31: DSRA / MRA | C31: Debt Service Reserve Account and Maintenance Reserve Account -- cash reserves set aside to cover, respectively, upcoming debt service and periodic major maintenance/overhaul costs.
... B36: Terminal value | C36: An estimate of the value of a business beyond the explicit forecast period, here approximated by applying an exit EV/EBITDA multiple to final-year EBITDA at loan maturity.

Sheet Charts
B2: Charts — Key Model Outputs (Active Scenario)
B4: Charts update live with the Cover-sheet scenario switcher. | G4: =Cover!$C$9 -> Base | H4: <<<< Cover
